Workbook
Name AdditionalOtherIncome: Inputs!$B$49
Name Address: Inputs!$B$10
Name AssetManagementFeeOfEgi: Inputs!$B$28
Name BadDebt: Inputs!$B$24
Name CommonExteriorCapex: Inputs!$B$35
Name ExitCapRate: Inputs!$B$18
Name ExpenseGrowth: Inputs!$B$22
Name HoldPeriodYears: Inputs!$B$17
Name IncomeGrowth: Inputs!$B$21
Name InteriorRenovationCostUnit: Inputs!$B$34
Name IrrTarget: Inputs!$B$47
Name LoanInterestRate: Inputs!$B$16
Name Ltv: Inputs!$B$15
Name ManagementFeeOfEgi: Inputs!$B$27
Name MiscellaneousExpenseAnnual: Inputs!$B$37
Name OtherRentalDeduction: Inputs!$B$29
Name PremiumPerUnit: Inputs!$B$31
Name PriceOverride: Inputs!$B$6
Name PropertyName: Inputs!$B$9
Name PurchaseCapRate: Inputs!$B$14
Name RentRoll_FirstDataRow: 'Rent Roll'!$A$23
Name RR_AsOf: 'Rent Roll'!$B$6
Name RR_OfficialOccupancy: 'Rent Roll'!$B$10
Name RR_OfficialOccupied: 'Rent Roll'!$B$8
Name RR_OfficialUnits: 'Rent Roll'!$B$7
Name RR_OfficialVacant: 'Rent Roll'!$B$9
Name SiteAcres: Inputs!$B$12
Name StabilizedOccupancyTarget: Inputs!$B$26
Name T12_Controllable: 'T12 Actuals'!$B$16
Name T12_EGI: 'T12 Actuals'!$B$10
Name T12_GPR: 'T12 Actuals'!$B$6
Name T12_Insurance: 'T12 Actuals'!$B$19
Name T12_NOI: 'T12 Actuals'!$B$23
Name T12_OpEx: 'T12 Actuals'!$B$22
Name T12_OtherIncome: 'T12 Actuals'!$B$9
Name T12_RawFirstRow: 'T12 Actuals'!$A$30
Name T12_Taxes: 'T12 Actuals'!$B$20
Name T12_Utilities: 'T12 Actuals'!$B$17
Name Tax_Millage: Tax!$B$9
Name Tax_NonAdValorem: Tax!$B$10
Name Tax_PIN: Tax!$B$6
Name Tax_TaxableValue: Tax!$B$8
Name TaxGrowth: Inputs!$B$23
Name UnitMix_FirstDataRow: 'Unit Mix'!$A$6
Name Units: Inputs!$B$13
Name UnitsRenovatedPerMonth: Inputs!$B$45
Name ValueAddUnits: Inputs!$B$30
Name YearBuilt: Inputs!$B$11
Name Tax_ReassessPct: Tax!$B$19

Sheet Dashboard
A1: =UPPER(Inputs!$B$9) -> RIVERBEND APARTMENTS
A2: =Inputs!$B$10&" | "&TEXT(Inputs!$B$13,"#,##0")&"-Unit Value-Add | Built "&Inputs!$B$11&" | "&TEXT(Inputs!$B$12,"0.00")&" Acres" -> 4100 Millrace Pointe Drive, Dayton, OH 45415 | 96-Unit Value-Add | Built 1987 | 7.40 Acres
A4: =Inputs!$B$13 -> 96 | B4: =Inputs!$B$11 -> 1987 | C4: =TEXT('Unit Mix'!$B$2,"#,##0")&" SF" -> 898 SF | D4: ='Rent Roll'!$B$10 -> 0.9375 | E4: =IFERROR('Rent Roll'!$B$19/Inputs!$B$13,0) -> 1089.5833 | F4: ='Rent Comps'!$L$12 -> 0.938
A5: UNITS | B5: YEAR BUILT | C5: AVG UNIT SIZE | D5: OCCUPANCY | E5: AVG RENT (IN-PLACE) | F5: MARKET OCC (OM COMPS)
A7: ='Debt & Exit'!$B$6 -> 8442177.4 | B7: =IFERROR('Debt & Exit'!$B$7,0) -> 87939.348 | C7: ='T12 Actuals'!$B$23 -> 523415 | D7: =IFERROR('Pro Forma'!$D$30,0) -> 484834.88 | E7: =Inputs!$B$36 -> 883600 | F7: ='Max Price Solver'!$B$42 -> 8912387.4
A8: PURCHASE PRICE | B8: PRICE PER DOOR | C8: T12 NOI | D8: YEAR 1 NOI | E8: TOTAL CAPEX | F8: MAX PRICE @ 16% IRR
A10: =IF(AND('Debt & Exit'!$B$25=0,'Debt & Exit'!$B$26<>1),"n/a",'Debt & Exit'!$B$25) -> 0.19043256 | B10: =IFERROR('Debt & Exit'!$B$26,0) -> 2.2099212 | C10: =IFERROR('Exit Scenarios'!$C$16,0) -> 0.10061883 | D10: =IFERROR('Pro Forma'!$D$30/'Debt & Exit'!$C$21,0) -> 1.4916903 | E10: =Inputs!$B$30*Inputs!$B$31*12 -> 146880 | F10: =Tax!$B$16-Tax!$B$12 -> 18482.996
A11: ="LEVERED IRR (SALE YR"&Inputs!$B$17&")" -> LEVERED IRR (SALE YR5) | B11: EQUITY MULTIPLE | C11: YR2 CASH-ON-CASH | D11: YEAR 1 DSCR | E11: NOI UPSIDE / YR | F11: TAX INCREASE / YR
A13: DETAILS - HOW EACH NUMBER IS BUILT
A14: Metric | B14: Value | C14: How calculated
A15: Units | B15: =Inputs!$B$13 -> 96 | C15: Linked to Inputs.
A16: T12 NOI | B16: ='T12 Actuals'!$B$23 -> 523415 | C16: Actual trailing-12 NOI.
A17: Purchase Price | B17: ='Debt & Exit'!$B$6 -> 8442177.4 | C17: T12 NOI / purchase cap rate, unless an override price is entered on Inputs.
A18: Price Per Unit | B18: =IFERROR('Debt & Exit'!$B$7,0) -> 87939.348 | C18: Purchase price / total units.
A19: Loan Amount | B19: ='Debt & Exit'!$B$8 -> 5909524.2 | C19: Purchase price x LTV.
A20: Initial Equity Required | B20: ='Debt & Exit'!$B$12 -> 3669518.5 | C20: Price + capex + closing - loan.
A21: Year 1 NOI | B21: =IFERROR('Pro Forma'!$D$30,0) -> 484834.88 | C21: In-place rent + partial loss-to-lease + reno premium net of downtime, less normalized expenses and reset taxes. Capex is NOT in NOI.
A22: Year 5 NOI | B22: ='Pro Forma'!$H$30 -> 771593.37 | C22: Full reno premium + income growth, less reset taxes.
A23: Year 8 NOI | B23: ='Pro Forma'!$K$30 -> 843140.9 | C23: Year 8 of the extended pro forma - drives the Year 8 exits.
A24: Year 1 DSCR | B24: =IFERROR('Pro Forma'!$D$30/'Debt & Exit'!$C$21,0) -> 1.4916903 | C24: Year 1 NOI / annual debt service.
A25: Levered IRR (hold-period sale) | B25: ='Debt & Exit'!$B$25 -> 0.19043256 | C25: Full equity cash flows through the Inputs hold period, incl. net sale proceeds.
A26: Equity Multiple | B26: =IFERROR('Debt & Exit'!$B$26,0) -> 2.2099212 | C26: Total distributions / initial equity.
A27: Current County Tax | B27: =Tax!$B$12 -> 165393 | C27: Taxable value x millage + non-ad valorem.
A28: New Tax After Sale | B28: =Tax!$B$16 -> 183876 | C28: Purchase price x millage + non-ad valorem (FL reassessment).
A29: Official Rent Roll Occupancy | B29: ='Rent Roll'!$B$10 -> 0.9375 | C29: From rent roll report summary.
A30: Current Avg Rent / Unit | B30: =IFERROR('Rent Roll'!$B$19/Inputs!$B$13,0) -> 1089.5833 | C30: In-place charges with vacant units counted at market rent, / total units.
A31: Target Avg Rent Post-Reno | B31: =IFERROR(('Rent Roll'!$B$16+Inputs!$B$30*Inputs!$B$31)/Inputs!$B$13,0) -> 1150.2604 | C31: Current in-place + value-add units x monthly premium, / total units.
A32: Market Avg Occupancy (OM comp set) | B32: ='Rent Comps'!$L$12 -> 0.938 | C32: Average of the comp set occupancy - compare to subject for occupancy upside.
A33: Units to Renovate | B33: =Inputs!$B$30 -> 72 | C33: Value-add units from Inputs.
A34: Total NOI Opportunity | B34: =Inputs!$B$30*Inputs!$B$31*12 -> 146880 | C34: Value-add units x monthly premium x 12, before downtime.
A35: Max Price to Hit IRR Target | B35: ='Max Price Solver'!$B$42 -> 8912387.4 | C35: Interpolated on the Max Price Solver tab, selling in the hold-period year.
A36: ...same, per unit | B36: ='Max Price Solver'!$B$43 -> 92837.369 | C36: Solved max price / total units.
A38: RETURNS vs TARGETS (detail on Exit Scenarios tab)
A39: Scenario | B39: IRR | C39: Equity Multiple | D39: IRR Target | E39: Status
A40: Sale Year 3 | B40: ='Exit Scenarios'!B14 -> 0.22213197 | C40: =IFERROR('Exit Scenarios'!B15,0) -> 1.7815366 | D40: =Inputs!$B$47 -> 0.16 | E40: ='Exit Scenarios'!$C$48 -> PASS
A41: Sale Year 5 | B41: ='Exit Scenarios'!C14 -> 0.19043256 | C41: =IFERROR('Exit Scenarios'!C15,0) -> 2.2099212 | D41: =Inputs!$B$47 -> 0.16 | E41: ='Exit Scenarios'!$C$49 -> PASS
A42: Sale Year 8 | B42: ='Exit Scenarios'!D14 -> 0.17158252 | C42: =IFERROR('Exit Scenarios'!D15,0) -> 2.9223389 | D42: =Inputs!$B$47 -> 0.16 | E42: ='Exit Scenarios'!$C$50 -> PASS
A43: Refi Yr3 + Sale Yr5 | B43: ='Exit Scenarios'!E14 -> 0.21428408 | C43: =IFERROR('Exit Scenarios'!E15,0) -> 2.1095883 | D43: =Inputs!$B$47 -> 0.16 | E43: ='Exit Scenarios'!$C$51 -> PASS
A44: Refi Yr3 + Sale Yr8 | B44: ='Exit Scenarios'!F14 -> 0.20717234 | C44: =IFERROR('Exit Scenarios'!F15,0) -> 2.7064833 | D44: =Inputs!$B$47 -> 0.16 | E44: ='Exit Scenarios'!$C$52 -> PASS
A45: Refi Yr5 + Sale Yr8 | B45: ='Exit Scenarios'!G14 -> 0.19016913 | C45: =IFERROR('Exit Scenarios'!G15,0) -> 2.7588606 | D45: =Inputs!$B$47 -> 0.16 | E45: ='Exit Scenarios'!$C$53 -> PASS
A46: Year 2 Cash-on-Cash | B46: =IFERROR('Exit Scenarios'!$C$16,0) -> 0.10061883 | D46: =Inputs!$B$48 -> 0.03 | E46: =IFERROR('Exit Scenarios'!$E$49,0) -> PASS
A48: Colour key: gold box = a number you can change (Inputs tab) | sage = read from your documents | white = calculated | red = needs verification

Sheet Inputs
A1: =Inputs!$B$9&" - Underwriting Inputs" -> Riverbend Apartments - Underwriting Inputs
A2: =B14 -> 0.062 | B2: =B15 -> 0.7 | C2: =B17 -> 5 | D2: =B47 -> 0.16 | E2: =IF(B6>0,B6,"Off (cap rate)") -> Off (cap rate) | F2: =B45 -> 6
A3: PURCHASE CAP RATE | B3: LTV | C3: HOLD PERIOD (YRS) | D3: IRR TARGET | E3: PRICE OVERRIDE | F3: UNITS RENOVATED/MO
A5: Input / Assumption | B5: Value | C5: Where it comes from (gold box = you can change it, sage = read from your documents)
A6: Purchase Price Override ($, 0 = T12 NOI / cap rate) | B6: 0 | C6: If > 0, this price replaces the cap-rate-derived purchase price everywhere: loan, equity, tax reset, returns, scenarios.
A7: Cap-Rate-Derived Price (reference) | B7: ='T12 Actuals'!$B$23/B14 -> 8442177.4 | C7: What the purchase price would be with the override off. To revert, clear the override above back to 0.
A8: Active Purchase Price (in use now) | B8: ='Debt & Exit'!$B$6 -> 8442177.4 | C8: Whichever of the two above is actually driving the model right now.
A9: Property Name | B9: Riverbend Apartments | C9: OM / county record. Text label only.
A10: Address | B10: 4100 Millrace Pointe Drive, Dayton, OH 45415 | C10: OM / public record. Text label only.
A11: Year Built | B11: 1987 | C11: OM / county record. Shown on Dashboard fast facts.
A12: Site Acres | B12: 7.4 | C12: OM / county record. Shown on Dashboard banner.
A13: Units | B13: 96 | C13: OM and rent roll. Used for price per door and per-unit checks.
A14: Purchase Cap Rate | B14: 0.062 | C14: Purchase price = T12 NOI / purchase cap rate.
A15: LTV | B15: 0.7 | C15: Debt = purchase price x LTV.
A16: Loan Interest Rate | B16: 0.055 | C16: Placeholder - source needed. Interest-only debt service = loan amount x rate.
A17: Hold Period (years) | B17: 5 | C17: Modeling assumption. THE hold-period switch: the model runs eight years and the sale lands in this year on Debt & Exit, the Dashboard, and the Max Price Solver. 1-8.
A18: Exit Cap Rate | B18: 0.06 | C18: Modeling assumption - source needed. Exit value = the hold-period year's NOI / exit cap rate.
A19: Disposition / Closing Cost at Exit | B19: 0.05 | C19: Prior 5% convention. Subtracted from exit sale proceeds only.
A20: Closing Cost | B20: 0.03 | C20: Closing cost = purchase price x 3%. Applies to acquisition/equity and return tabs.
A21: Income Growth | B21: 0.03 | C21: Income grows 3% YoY after value-add bump, Years 2-8.
A22: Expense Growth | B22: 0.03 | C22: Non-tax operating expenses grow 3% YoY, Years 2-8.
... A24: Bad Debt % | B24: 0.02 | C24: Bad debt = adjusted gross potential rent x 2%.
A25: Vacancy % | B25: =1-'Rent Roll'!$B$10 -> 0.0625 | C25: Calculated from rent roll. Vacancy % = 1 - official rent-roll occupancy.
A26: Stabilized Occupancy Target % | B26: 0.96
A27: Management Fee % of EGI | B27: 0.03 | C27: Management fee = EGI x 3%.
A28: Asset Management Fee % of EGI | B28: 0.02 | C28: Asset management fee = EGI x 2%.
A29: Concessions (annual $) | B29: =B13*B50*B51*'Rent Roll'!$B$2 -> 17433.333 | C29: Concessions = units x share turning x months of rent x avg rent/unit (factors below). Grown with income growth in the pro forma.
A30: Value-Add Units | B30: 72 | C30: OM value-add plan. Used in renovation premium calculation.
A31: Value-Add Premium / Unit / Month | B31: 170 | C31: OM value-add plan. Monthly premium = online renovated units x $255.
A32: Renovation Downtime (months of rent lost per renovated unit) | B32: 1 | C32: Single downtime input: each renovated unit loses this many months of rent (renovations happen at lease turnover). Also drives the units-under-renovation schedule column on Reno Pace.
A33: Renovation Online Start Month | B33: 3 | C33: First completed/online batch starts in month 3; monthly pace continues thereafter.
A34: Interior Renovation Cost / Unit | B34: 8800 | C34: Prior model / needs confirmation. Interior capex = units x cost per unit.
A35: Common / Exterior Capex | B35: 250000 | C35: Prior model / needs confirmation. Added to total capex.
A36: Total Capex | B36: =B30*B34+B35 -> 883600 | C36: Calculated by model. Total capex = value-add units x interior cost/unit + common/exterior capex.
A37: Miscellaneous Expense (One-Time, Year 1 Only) | B37: 10000 | C37: One-time expense charged in Year 1 only. Does not recur or grow in Years 2-8.
A39: ADDED - SCENARIOS, PHASING & DEBT STRUCTURE
A40: Refi Cap Rate | B40: 0.0595 | C40: Modeling assumption. Refi value = the refi year's NOI / this cap. Exit Scenarios models a Year 3 and a Year 5 refinance.
A41: Refi LTV | B41: 0.7 | C41: New loan = refi value x this LTV.
A42: Refi Closing Cost % | B42: 0.01 | C42: Modeling assumption. Cost = new loan x this %.
A43: Refi Interest Rate | B43: 0.0545 | C43: Placeholder - needs quote. New debt service after refi, on both the Year 3 and Year 5 refi cases.
A44: Loss-to-Lease Capture in Year 1 % | B44: 0.5 | C44: Modeling assumption. Yr1 rent = in-place + LTL x this %; full market by Yr2.
A45: Units Renovated Per Month | B45: 6 | C45: Modeling assumption. Drives completed/online units per month on Reno Pace tab.
A46: Amortization Period (yrs, 0=Interest-Only) | B46: 0 | C46: Modeling toggle. 0 = interest-only. >0 = amortizing debt service (PMT) and principal paydown.
A47: IRR Target | B47: 0.16 | C47: Scenario IRRs are scored PASS/FLAG vs. this.
A48: Year 2 Cash-on-Cash Target | B48: 0.03 | C48: Yr2 CoC scored PASS/FLAG vs. this.
A49: Additional Other Income (Annual $, e.g. parking, pet, storage not yet charged) | B49: 0 | C49: Value-add upside / estimate. Ancillary income not currently charged. Added to the Other Income line from Year 1, then grown with income growth. 0 = none.
A50: Share of Units Turning / Year | B50: 0.33333333 | C50: Modeling assumption. Fraction of units that turn each year. Drives BOTH the concession estimate above and the turnover benchmark below.
A51: Concession: Months of Rent per Turned Unit | B51: 0.5 | C51: Modeling assumption. Concession granted per turned unit, in months of average rent (0.5 = half a month).
A52: ADDED - HOUSE EXPENSE BENCHMARKS (house numbers, 2026-08-10)
A53: Turnover / Make-Ready Benchmark ($ per TURNED unit) | B53: 330 | C53: House benchmark. Quoted per unit that TURNS, not per unit in the property — the Pro Forma benchmark cell converts it with the turn share above. 0 = use the T12 turnover figure.
A54: Replacement Reserves ($/unit/yr) | B54: 250 | C54: House benchmark. Charged BELOW NOI on the Pro Forma, so it does not change NOI, the purchase price, the exit values or the IRR — only cash flow after reserves. Grows with expense growth. 0 = no reserve line.
A55: Max Total Opex as % of EGI | B55: 0.56 | C55: House ceiling. Year 1 total operating expenses are scored against this on the Checks tab. 0 = not scored.

Sheet T12 Actuals
A1: T12 Actuals - Summary
A2: =B23 -> 523415 | B2: =B10 -> 1231000 | C2: =B22 -> 707585 | D2: =IFERROR(B23/B10,0) -> 0.42519496
A3: T12 NOI | B3: T12 EGI | C3: TOTAL OPEX | D3: NOI MARGIN
A4: Summary of the uploaded T12. Raw monthly account detail is pasted below.
A5: Line | B5: T12 Amount | C5: Notes
A6: Gross Potential Rent | B6: 1305600 | C6: Starting point only. Source T12 number. Year 1 underwrite uses rent roll market rent instead.
A7: Less: vacancy, concessions, bad debt | B7: -166500 | C7: Used to understand actual drag. Company underwrite normalizes key items instead of blindly using this total.
A8: Net Rental Income | B8: 1139100 | C8: Reference point. Source T12 number.
A9: Other Income | B9: 91900 | C9: Pro forma starts here. Year 1 grows this by 3%.
A10: Effective Gross Income (EGI) | B10: 1231000 | C10: Fee base / margin check. Used as actual T12 benchmark.
A11: Repairs & Maintenance | B11: 70700 | C11: Total Repairs and Maintenance section of the RM T12.
A12: Turnover Costs | B12: 26600 | C12: Total Turnover Costs section of the RM T12.
A13: Labor Costs (Payroll) | B13: 123000 | C13: Total Labor Costs section of the RM T12.
A14: Advertising & Promotions | B14: 15800 | C14: Total Advertising and Promotions section of the RM T12.
A15: General & Administrative | B15: 27700 | C15: Total General and Administrative Costs section of the RM T12.
A16: Controllable Expenses | B16: 263800 | C16: Sum of the five sections above. Pro forma expense base — each section grows 3%/yr (or uses its benchmark).
A17: Utilities | B17: 121500 | C17: Pro forma expense base. Year 1 grows by 3%.
... A26: Actual Concessions - net | B26: -11800 | C26: Used as a deduction ratio. Converted to % of GPR for underwriting.
A28: Raw monthly account detail below - use this only if you need to trace the T12 summary back to individual account lines.
A29: Source Row | B29: Account | C29: Label | D29: Oct 2025 | E29: Nov 2025 | F29: Dec 2025 | G29: Jan 2026 | H29: Feb 2026 | I29: Mar 2026 | J29: Apr 2026 | K29: May 2026 | L29: Jun 2026 | M29: Jul 2026 | N29: Aug 2026 | O29: Sep 2026 | P29: Total | Q29: Category
A30: 7 | C30: INCOME | P30: =SUM(D30:O30) -> 0
A31: 8 | C31: Rental Income | P31: =SUM(D31:O31) -> 0
A32: 9 | B32: 4000-00 | C32: Gross Potential Rent | D32: 105210 | E32: 105862 | F32: 106515 | G32: 107168 | H32: 107821 | I32: 108474 | J32: 109126 | K32: 109779 | L32: 110432 | M32: 111085 | N32: 111738 | O32: 112390 | P32: =SUM(D32:O32) -> 1305600
A33: 10 | C33: Total Gross Potential Rent | D33: 105210 | E33: 105862 | F33: 106515 | G33: 107168 | H33: 107821 | I33: 108474 | J33: 109126 | K33: 109779 | L33: 110432 | M33: 111085 | N33: 111738 | O33: 112390 | P33: =SUM(D33:O33) -> 1305600
A34: 11 | B34: 4510-00 | C34: Vacancy Loss | D34: -7090 | E34: -6109 | F34: -6828 | G34: -6246 | H34: -7784 | I34: -6308 | J34: -7052 | K34: -7921 | L34: -7122 | M34: -8087 | N34: -6093 | O34: -8260 | P34: =SUM(D34:O34) -> -84900
A35: 12 | B35: 4510-01 | C35: Vacancy - Model/Down Units | D35: 0 | E35: 0 | F35: 0 | G35: 0 | H35: 0 | I35: 0 | J35: 0 | K35: 0 | L35: 0 | M35: 0 | N35: 0 | O35: 0 | P35: =SUM(D35:O35) -> 0
A36: 13 | B36: 4520-00 | C36: Loss to Lease | D36: -4722 | E36: -4711 | F36: -4569 | G36: -4675 | H36: -4900 | I36: -5024 | J36: -4981 | K36: -4797 | L36: -4697 | M36: -4728 | N36: -5028 | O36: -4568 | P36: =SUM(D36:O36) -> -57400
A37: 14 | B37: 4530-00 | C37: Concessions | D37: -830 | E37: -1002 | F37: -929 | G37: -646 | H37: -879 | I37: -953 | J37: -709 | K37: -824 | L37: -1250 | M37: -1497 | N37: -1258 | O37: -1023 | P37: =SUM(D37:O37) -> -11800
A38: 15 | B38: 4535-00 | C38: Concessions - Other | D38: 0 | E38: 0 | F38: 0 | G38: 0 | H38: 0 | I38: 0 | J38: 0 | K38: 0 | L38: 0 | M38: 0 | N38: 0 | O38: 0 | P38: =SUM(D38:O38) -> 0
A39: 16 | B39: 4540-00 | C39: Bad Debt Write-offs | D39: -1455 | E39: -986 | F39: -1103 | G39: -1411 | H39: -1007 | I39: -1220 | J39: -951 | K39: -1239 | L39: -1964 | M39: -2006 | N39: -996 | O39: -962 | P39: =SUM(D39:O39) -> -15300
A40: 17 | B40: 4545-00 | C40: Bad Debt Recovery | D40: 316 | E40: 316 | F40: 339 | G40: 160 | H40: 219 | I40: 187 | J40: 182 | K40: 264 | L40: 255 | M40: 260 | N40: 138 | O40: 264 | P40: =SUM(D40:O40) -> 2900
A41: 18 | C41: Total Deductions | D41: -13781 | E41: -12492 | F41: -13090 | G41: -12818 | H41: -14351 | I41: -13318 | J41: -13511 | K41: -14517 | L41: -14778 | M41: -16058 | N41: -13237 | O41: -14549 | P41: =SUM(D41:O41) -> -166500
A42: 19 | C42: Net Rental Income | D42: 91429 | E42: 93370 | F42: 93425 | G42: 94350 | H42: 93470 | I42: 95156 | J42: 95615 | K42: 95262 | L42: 95654 | M42: 95027 | N42: 98501 | O42: 97841 | P42: =SUM(D42:O42) -> 1139100
A43: 20 | C43: Other Income | P43: =SUM(D43:O43) -> 0
A44: 21 | B44: 4700-00 | C44: Utility Reimbursement (RUBS) | D44: 3744 | E44: 3824 | F44: 3835 | G44: 3744 | H44: 3755 | I44: 4744 | J44: 4801 | K44: 4496 | L44: 4645 | M44: 4576 | N44: 3861 | O44: 3775 | P44: =SUM(D44:O44) -> 49800
A45: 22 | B45: 4710-00 | C45: Late Fees | D45: 709 | E45: 749 | F45: 909 | G45: 658 | H45: 801 | I45: 736 | J45: 646 | K45: 760 | L45: 892 | M45: 915 | N45: 877 | O45: 648 | P45: =SUM(D45:O45) -> 9300
A46: 23 | B46: 4720-00 | C46: Application and Admin Fees | D46: 564 | E46: 582 | F46: 547 | G46: 558 | H46: 608 | I46: 568 | J46: 465 | K46: 583 | L46: 577 | M46: 787 | N46: 611 | O46: 450 | P46: =SUM(D46:O46) -> 6900
A47: 24 | B47: 4730-00 | C47: Pet Rent and Fees | D47: 1077 | E47: 1107 | F47: 1055 | G47: 1097 | H47: 1132 | I47: 1056 | J47: 1030 | K47: 1174 | L47: 1164 | M47: 1154 | N47: 1061 | O47: 1093 | P47: =SUM(D47:O47) -> 13200
A48: 25 | B48: 4740-00 | C48: Laundry and Vending | D48: 349 | E48: 323 | F48: 319 | G48: 331 | H48: 330 | I48: 342 | J48: 373 | K48: 338 | L48: 317 | M48: 362 | N48: 372 | O48: 344 | P48: =SUM(D48:O48) -> 4100
A49: 26 | B49: 4750-00 | C49: Parking, Storage and Other | D49: 809 | E49: 732 | F49: 702 | G49: 727 | H49: 831 | I49: 674 | J49: 650 | K49: 633 | L49: 686 | M49: 713 | N49: 643 | O49: 800 | P49: =SUM(D49:O49) -> 8600
A50: 27 | C50: Total Other Income | D50: 7252 | E50: 7317 | F50: 7367 | G50: 7115 | H50: 7457 | I50: 8120 | J50: 7965 | K50: 7984 | L50: 8281 | M50: 8507 | N50: 7425 | O50: 7110 | P50: =SUM(D50:O50) -> 91900
A51: 28 | C51: Total Income | D51: 98681 | E51: 100687 | F51: 100792 | G51: 101465 | H51: 100927 | I51: 103276 | J51: 103580 | K51: 103246 | L51: 103935 | M51: 103534 | N51: 105926 | O51: 104951 | P51: =SUM(D51:O51) -> 1231000
A52: 30 | C52: EXPENSES | P52: =SUM(D52:O52) -> 0
A53: 31 | C53: Controllable Expenses | P53: =SUM(D53:O53) -> 0
A54: 32 | B54: 6110-00 | C54: Repairs - Supplies | D54: 1698 | E54: 2160 | F54: 1484 | G54: 1856 | H54: 1541 | I54: 2148 | J54: 1911 | K54: 1781 | L54: 1993 | M54: 1555 | N54: 2131 | O54: 2042 | P54: =SUM(D54:O54) -> 22300
A55: 33 | B55: 6120-00 | C55: Contract Services (HVAC, plumbing, appliance) | D55: 2043 | E55: 2053 | F55: 2180 | G55: 2384 | H55: 1834 | I55: 2399 | J55: 2368 | K55: 2340 | L55: 2139 | M55: 2525 | N55: 2108 | O55: 2527 | P55: =SUM(D55:O55) -> 26900
A56: 34 | B56: 6130-00 | C56: Grounds and Landscaping | D56: 1190 | E56: 1070 | F56: 1151 | G56: 1222 | H56: 1146 | I56: 1405 | J56: 1565 | K56: 1403 | L56: 1556 | M56: 1420 | N56: 1202 | O56: 1070 | P56: =SUM(D56:O56) -> 15400
A57: 35 | B57: 6140-00 | C57: Snow Removal and Common Area | D57: 546 | E57: 452 | F57: 482 | G57: 597 | H57: 706 | I57: 355 | J57: 562 | K57: 402 | L57: 534 | M57: 460 | N57: 548 | O57: 456 | P57: =SUM(D57:O57) -> 6100
A58: 36 | C58: Total Repairs and Maintenance | D58: 5477 | E58: 5735 | F58: 5297 | G58: 6059 | H58: 5227 | I58: 6307 | J58: 6406 | K58: 5926 | L58: 6222 | M58: 5960 | N58: 5989 | O58: 6095 | P58: =SUM(D58:O58) -> 70700
A59: 37 | B59: 6210-00 | C59: Make-Ready - Flooring | D59: 858 | E59: 759 | F59: 940 | G59: 951 | H59: 761 | I59: 752 | J59: 859 | K59: 1337 | L59: 969 | M59: 1035 | N59: 1095 | O59: 884 | P59: =SUM(D59:O59) -> 11200
A60: 38 | B60: 6220-00 | C60: Make-Ready - Paint and Cleaning | D60: 736 | E60: 803 | F60: 742 | G60: 826 | H60: 601 | I60: 761 | J60: 856 | K60: 1100 | L60: 1042 | M60: 802 | N60: 1032 | O60: 799 | P60: =SUM(D60:O60) -> 10100
A61: 39 | B61: 6230-00 | C61: Make-Ready - Appliances | D61: 292 | E61: 409 | F61: 432 | G61: 450 | H61: 438 | I61: 298 | J61: 397 | K61: 454 | L61: 389 | M61: 649 | N61: 648 | O61: 444 | P61: =SUM(D61:O61) -> 5300
A62: 40 | C62: Total Turnover Costs | D62: 1886 | E62: 1971 | F62: 2114 | G62: 2227 | H62: 1800 | I62: 1811 | J62: 2112 | K62: 2891 | L62: 2400 | M62: 2486 | N62: 2775 | O62: 2127 | P62: =SUM(D62:O62) -> 26600
A63: 41 | B63: 6310-00 | C63: On-Site Salaries | D63: 8425 | E63: 8561 | F63: 8477 | G63: 8534 | H63: 8428 | I63: 8423 | J63: 8472 | K63: 8447 | L63: 8458 | M63: 8480 | N63: 8509 | O63: 8386 | P63: =SUM(D63:O63) -> 101600
A64: 42 | B64: 6320-00 | C64: Payroll Taxes and Benefits | D64: 1855 | E64: 1774 | F64: 1745 | G64: 1832 | H64: 1764 | I64: 1801 | J64: 1734 | K64: 1779 | L64: 1715 | M64: 1836 | N64: 1723 | O64: 1842 | P64: =SUM(D64:O64) -> 21400
A65: 43 | C65: Total Labor Costs | D65: 10280 | E65: 10335 | F65: 10222 | G65: 10366 | H65: 10192 | I65: 10224 | J65: 10206 | K65: 10226 | L65: 10173 | M65: 10316 | N65: 10232 | O65: 10228 | P65: =SUM(D65:O65) -> 123000
A66: 44 | B66: 6410-00 | C66: Internet Listings and Marketing | D66: 1355 | E66: 1236 | F66: 1320 | G66: 1237 | H66: 1291 | I66: 1211 | J66: 1170 | K66: 1564 | L66: 1318 | M66: 1466 | N66: 1601 | O66: 1031 | P66: =SUM(D66:O66) -> 15800
A67: 45 | C67: Total Advertising and Promotions | D67: 1355 | E67: 1236 | F67: 1320 | G67: 1237 | H67: 1291 | I67: 1211 | J67: 1170 | K67: 1564 | L67: 1318 | M67: 1466 | N67: 1601 | O67: 1031 | P67: =SUM(D67:O67) -> 15800
A68: 46 | B68: 6510-00 | C68: Office and Supplies | D68: 654 | E68: 550 | F68: 585 | G68: 595 | H68: 551 | I68: 701 | J68: 592 | K68: 637 | L68: 570 | M68: 669 | N68: 636 | O68: 560 | P68: =SUM(D68:O68) -> 7300
A69: 47 | B69: 6520-00 | C69: Software and Telephone | D69: 840 | E69: 820 | F69: 850 | G69: 833 | H69: 800 | I69: 828 | J69: 817 | K69: 851 | L69: 804 | M69: 799 | N69: 797 | O69: 861 | P69: =SUM(D69:O69) -> 9900
A70: 48 | B70: 6530-00 | C70: Legal and Professional | D70: 322 | E70: 636 | F70: 546 | G70: 558 | H70: 642 | I70: 428 | J70: 750 | K70: 633 | L70: 665 | M70: 507 | N70: 613 | O70: 800 | P70: =SUM(D70:O70) -> 7100
A71: 49 | B71: 6540-00 | C71: Licenses and Fees | D71: 305 | E71: 279 | F71: 271 | G71: 313 | H71: 260 | I71: 260 | J71: 302 | K71: 296 | L71: 262 | M71: 293 | N71: 264 | O71: 295 | P71: =SUM(D71:O71) -> 3400
A72: 50 | C72: Total General and Administrative Costs | D72: 2121 | E72: 2285 | F72: 2252 | G72: 2299 | H72: 2253 | I72: 2217 | J72: 2461 | K72: 2417 | L72: 2301 | M72: 2268 | N72: 2310 | O72: 2516 | P72: =SUM(D72:O72) -> 27700
A73: 51 | C73: Total Controllable Expenses | D73: 21119 | E73: 21562 | F73: 21205 | G73: 22188 | H73: 20763 | I73: 21770 | J73: 22355 | K73: 23024 | L73: 22414 | M73: 22496 | N73: 22907 | O73: 21997 | P73: =SUM(D73:O73) -> 263800
A74: 52 | B74: 6610-00 | C74: Electric - Common Area | D74: 1876 | E74: 1891 | F74: 1932 | G74: 1783 | H74: 1870 | I74: 2322 | J74: 2272 | K74: 2321 | L74: 2278 | M74: 2279 | N74: 1910 | O74: 1866 | P74: =SUM(D74:O74) -> 24600
A75: 53 | B75: 6620-00 | C75: Water and Sewer | D75: 5384 | E75: 5207 | F75: 5122 | G75: 5299 | H75: 5273 | I75: 6380 | J75: 6343 | K75: 6709 | L75: 6954 | M75: 6530 | N75: 5741 | O75: 5458 | P75: =SUM(D75:O75) -> 70400
A76: 54 | B76: 6630-00 | C76: Gas - Common Area | D76: 296 | E76: 308 | F76: 418 | G76: 351 | H76: 421 | I76: 280 | J76: 305 | K76: 245 | L76: 272 | M76: 237 | N76: 308 | O76: 259 | P76: =SUM(D76:O76) -> 3700
A77: 55 | B77: 6640-00 | C77: Trash Removal | D77: 1946 | E77: 1872 | F77: 1933 | G77: 1912 | H77: 1875 | I77: 1882 | J77: 1873 | K77: 1907 | L77: 1908 | M77: 1912 | N77: 1873 | O77: 1907 | P77: =SUM(D77:O77) -> 22800
A78: 56 | C78: Total Utility Costs | D78: 9502 | E78: 9278 | F78: 9405 | G78: 9345 | H78: 9439 | I78: 10864 | J78: 10793 | K78: 11182 | L78: 11412 | M78: 10958 | N78: 9832 | O78: 9490 | P78: =SUM(D78:O78) -> 121500
A79: 57 | B79: 6700-00 | C79: Management Fee | D79: 3454 | E79: 3524 | F79: 3528 | G79: 3551 | H79: 3532 | I79: 3615 | J79: 3625 | K79: 3614 | L79: 3638 | M79: 3624 | N79: 3707 | O79: 3673 | P79: =SUM(D79:O79) -> 43085
A80: 58 | C80: Total Management Fees | D80: 3454 | E80: 3524 | F80: 3528 | G80: 3551 | H80: 3532 | I80: 3615 | J80: 3625 | K80: 3614 | L80: 3638 | M80: 3624 | N80: 3707 | O80: 3673 | P80: =SUM(D80:O80) -> 43085
A81: 59 | B81: 6800-00 | C81: Property and Liability Insurance | D81: 0 | E81: 0 | F81: 45900 | G81: 0 | H81: 0 | I81: 0 | J81: 0 | K81: 0 | L81: 45900 | M81: 0 | N81: 0 | O81: 0 | P81: =SUM(D81:O81) -> 91800
A82: 60 | C82: Total Insurance and Bonds | D82: 0 | E82: 0 | F82: 45900 | G82: 0 | H82: 0 | I82: 0 | J82: 0 | K82: 0 | L82: 45900 | M82: 0 | N82: 0 | O82: 0 | P82: =SUM(D82:O82) -> 91800
A83: 61 | B83: 6900-00 | C83: Real Estate Taxes | D83: 0 | E83: 0 | F83: 82700 | G83: 0 | H83: 0 | I83: 0 | J83: 0 | K83: 0 | L83: 82700 | M83: 0 | N83: 0 | O83: 0 | P83: =SUM(D83:O83) -> 165400
A84: 62 | C84: Total Property Taxes | D84: 0 | E84: 0 | F84: 82700 | G84: 0 | H84: 0 | I84: 0 | J84: 0 | K84: 0 | L84: 82700 | M84: 0 | N84: 0 | O84: 0 | P84: =SUM(D84:O84) -> 165400
A85: 63 | B85: 7010-00 | C85: Pest Control | D85: 625 | E85: 587 | F85: 598 | G85: 614 | H85: 593 | I85: 582 | J85: 607 | K85: 610 | L85: 588 | M85: 588 | N85: 623 | O85: 585 | P85: =SUM(D85:O85) -> 7200
A86: 64 | B86: 7020-00 | C86: Security and Courtesy Patrol | D86: 823 | E86: 784 | F86: 794 | G86: 790 | H86: 808 | I86: 817 | J86: 814 | K86: 767 | L86: 822 | M86: 795 | N86: 786 | O86: 800 | P86: =SUM(D86:O86) -> 9600
A87: 65 | B87: 7030-00 | C87: Other Property Expenses | D87: 520 | E87: 531 | F87: 357 | G87: 409 | H87: 323 | I87: 583 | J87: 336 | K87: 340 | L87: 438 | M87: 398 | N87: 561 | O87: 404 | P87: =SUM(D87:O87) -> 5200
A88: 66 | C88: Total Other Property Expenses | D88: 1968 | E88: 1902 | F88: 1749 | G88: 1813 | H88: 1724 | I88: 1982 | J88: 1757 | K88: 1717 | L88: 1848 | M88: 1781 | N88: 1970 | O88: 1789 | P88: =SUM(D88:O88) -> 22000
A89: 67 | C89: Total Operating Expenses | D89: 36043 | E89: 36266 | F89: 164487 | G89: 36897 | H89: 35458 | I89: 38231 | J89: 38530 | K89: 39537 | L89: 167912 | M89: 38859 | N89: 38416 | O89: 36949 | P89: =SUM(D89:O89) -> 707585
A90: 68 | C90: Net Operating Income | D90: 62638 | E90: 64421 | F90: -63695 | G90: 64568 | H90: 65469 | I90: 65045 | J90: 65050 | K90: 63709 | L90: -63977 | M90: 64675 | N90: 67510 | O90: 68002 | P90: =SUM(D90:O90) -> 523415

Sheet Rent Roll
A1: Rent Roll - Source, Parsed Audit, and Unit Detail
A2: =B10 -> 0.9375 | B2: =IFERROR(B19/Inputs!$B$13,0) -> 1089.5833 | C2: =B9 -> 6 | D2: =B17 -> 10950
A3: OFFICIAL OCCUPANCY | B3: ADJ AVG RENT/UNIT | C3: VACANT UNITS | D3: LOSS-TO-LEASE (MO)
A5: Metric | B5: Value | C5: Source | D5: How/Why | E5: Flag | F5: Note
A6: Report As Of | B6: 46310 | C6: Rent roll source | D6: Report date from uploaded rent roll. | E6: Source
A7: Official Units | B7: 96 | C7: Rent roll summary / OM | D7: Source unit count. | E7: Source
A8: Official Occupied Units | B8: 90 | C8: Rent roll report summary | D8: Source occupied count from report summary. | E8: Source
A9: Official Vacant Units | B9: 6 | C9: Rent roll report summary | D9: Source vacant count from report summary. | E9: Source
A10: Official Occupancy | B10: 0.9375 | C10: Rent roll report summary | D10: Official occupancy % from rent roll summary. | E10: Source
A11: Parsed Unit Count | B11: =COUNTA(A23:A2022) -> 96 | C11: Calculated from unit-level rows | D11: COUNTA of unit numbers in the parsed unit table. | E11: Calculated | F11: Audit ties to source unit count.
A12: Parsed Occupied Units | B12: =SUM(M23:M2022) -> 90 | C12: Calculated from rent charge flag | D12: SUM of occupied flags where rent charge is present. | E12: Calculated | F12: Parser count can differ from official summary.
A13: Parsed Vacant Units | B13: =B11-B12 -> 6 | C13: Calculated from unit-level rows | D13: Parsed unit count minus parsed occupied units. | E13: Calculated | F13: Audit item.
A14: Parsed Occupancy | B14: =IFERROR(B12/B11,0) -> 0.9375 | C14: Calculated from unit-level rows | D14: Parsed occupied units / parsed unit count. | E14: Calculated | F14: Compare to official occupancy.
A15: Monthly Market Rent | B15: =SUM(F23:F2022) -> 109135 | C15: Calculated from unit-level rows | D15: SUM of market rent column. | E15: Calculated | F15: Annualizes into Year 1 base GPR.
A16: Monthly In-place Rent Charges | B16: =SUM(G23:G2022) -> 98185 | C16: Calculated from unit-level rows | D16: SUM of rent charge column. | E16: Calculated | F16: Shows actual rent roll charge base.
A17: Monthly Loss-to-Lease | B17: =B15-B16 -> 10950 | C17: Calculated from unit-level rows | D17: Monthly market rent minus rent charges. | E17: Calculated | F17: Shows embedded rent gap before renovations.
A18: Total Resident Balance | B18: =SUM(L23:L2022) -> 3760 | C18: Calculated from unit-level rows | D18: SUM of balance column. | E18: Calculated | F18: Collections / bad debt diligence item.
A19: Adjusted Monthly Rent (vacants at market) | B19: =B16+SUMPRODUCT((G23:G2022=0)*(F23:F2022)) -> 104600 | C19: Calculated from unit-level rows | D19: In-place rent charges plus market rent for vacant units, so $0 vacant charges do not drag the average down. | E19: Calculated
A22: Unit | B22: Unit Type | C22: SqFt | D22: Resident ID | E22: Resident Name | F22: Market Rent | G22: Rent Charge | H22: Total Charges | I22: Move In | J22: Lease Expiration | K22: Move Out | L22: Balance | M22: Occupied Flag | N22: Loss to Lease | O22: Status Section
A23: A101 | B23: A1 | C23: 720 | D23: R100200 | E23: Mbeki, Imani | F23: 965 | G23: 915 | H23: 915 | I23: 46060 | J23: 46424 | L23: 0 | M23: 1 | N23: 117 | O23: Current/Notice/Vacant Residents
A24: A102 | B24: B2 | C24: 1032 | D24: R100207 | E24: Yoder, Devon | F24: 1235 | G24: 1135 | H24: 1135 | I24: 46099 | J24: 46463 | L24: 0 | M24: 1 | N24: 158 | O24: Current/Notice/Vacant Residents
A25: A103 | B25: B1 | C25: 932 | D25: R100214 | E25: Lindqvist, Aaliyah | F25: 1160 | G25: 1090 | H25: 1090 | I25: 45682 | J25: 46411 | L25: 0 | M25: 1 | N25: -22 | O25: Current/Notice/Vacant Residents
A26: A104 | B26: B1 | C26: 918 | D26: R100221 | E26: Sandoval, Elena | F26: 1150 | G26: 1105 | H26: 1105 | I26: 46049 | J26: 46413 | L26: 0 | M26: 1 | N26: 87 | O26: Current/Notice/Vacant Residents
A27: A201 | B27: A1 | C27: 712 | D27: R100228 | E27: Brennan, Marcus | F27: 985 | G27: 955 | H27: 955 | I27: 45329 | J27: 46423 | L27: 0 | M27: 1 | N27: 208 | O27: Current/Notice/Vacant Residents
A28: A202 | B28: B1 | C28: 924 | D28: R100235 | E28: Espinoza, Andre | F28: 1150 | G28: 1090 | H28: 1090 | I28: 46134 | J28: 46498 | L28: 0 | M28: 1 | N28: -33 | O28: Current/Notice/Vacant Residents
A29: A203 | B29: B1 | C29: 924 | D29: R100242 | E29: Quill, Priya | F29: 1140 | G29: 1070 | H29: 1070 | I29: 45994 | J29: 46358 | L29: 0 | M29: 1 | N29: 86 | O29: Current/Notice/Vacant Residents
A30: A204 | B30: B2 | C30: 1046 | D30: R100249 | E30: Dunmore, Tyrone | F30: 1250 | G30: 1200 | H30: 1200 | I30: 45560 | J30: 46654 | L30: 0 | M30: 1 | N30: -21 | O30: Current/Notice/Vacant Residents
A31: A301 | B31: B1 | C31: 924 | D31: R100256 | E31: Espinoza, Rosa | F31: 1160 | G31: 1160 | H31: 1160 | I31: 45540 | J31: 46634 | L31: 75 | M31: 1 | N31: -55 | O31: Current/Notice/Vacant Residents
A32: A302 | B32: A1 | C32: 706 | D32: R100263 | E32: Brennan, Victor | F32: 980 | G32: 950 | H32: 950 | I32: 46046 | J32: 46410 | L32: 0 | M32: 1 | N32: 48 | O32: Current/Notice/Vacant Residents
A33: A303 | B33: B1 | C33: 932 | D33: R100270 | E33: Brennan, Elena | F33: 1160 | G33: 1065 | H33: 1065 | I33: 45468 | J33: 46562 | L33: 0 | M33: 1 | N33: 1699 | O33: Current/Notice/Vacant Residents
A34: A304 | B34: C1 | C34: 1212 | D34: R100277 | E34: Gutierrez, Owen | F34: 1440 | G34: 1410 | H34: 1410 | I34: 46167 | J34: 46531 | L34: 0 | M34: 1 | N34: -77 | O34: Current/Notice/Vacant Residents
... A37: B103 | B37: B1 | C37: 932 | D37: R100298 | E37: Alvarez, Victor | F37: 1150 | G37: 1080 | H37: 1080 | I37: 46126 | J37: 46490 | L37: 0 | M37: 1 | N37: 142 | O37: Current/Notice/Vacant Residents
A38: B104 | B38: A1 | C38: 712 | F38: 975 | G38: 0 | H38: 0 | K38: 46279 | L38: 0 | M38: 0 | N38: 52 | O38: Current/Notice/Vacant Residents
A39: B201 | B39: B1 | C39: 918 | D39: R100312 | E39: Iverson, Hannah | F39: 1150 | G39: 1150 | H39: 1150 | I39: 45973 | J39: 46337 | L39: 320 | M39: 1 | N39: 1674 | O39: Current/Notice/Vacant Residents
A40: B202 | B40: A1 | C40: 712 | D40: R100319 | E40: Castellano, Felix | F40: 975 | G40: 975 | H40: 975 | I40: 45313 | J40: 46407 | L40: 0 | M40: 1 | N40: -77 | O40: Current/Notice/Vacant Residents
A41: B203 | B41: A1 | C41: 720 | D41: R100326 | E41: Mbeki, Luis | F41: 975 | G41: 945 | H41: 945 | I41: 45688 | J41: 46417 | L41: 0 | M41: 1 | N41: -23 | O41: Current/Notice/Vacant Residents
A42: B204 | B42: B1 | C42: 932 | D42: R100333 | E42: Ellison, Sofia | F42: 1155 | G42: 1120 | H42: 1120 | I42: 45382 | J42: 46476 | L42: 0 | M42: 1 | N42: 0 | O42: Current/Notice/Vacant Residents
A43: B301 | B43: A1 | C43: 720 | D43: R100340 | E43: Hawkins, Mei | F43: 965 | G43: 905 | H43: 905 | I43: 45411 | J43: 46505 | L43: 0 | M43: 1 | N43: 25 | O43: Current/Notice/Vacant Residents
A44: B302 | B44: A1 | C44: 712 | D44: R100347 | E44: Kowalski, Marcus | F44: 975 | G44: 975 | H44: 975 | I44: 46091 | J44: 46455 | L44: 0 | M44: 1 | N44: 87 | O44: Current/Notice/Vacant Residents
A45: B303 | B45: C1 | C45: 1204 | D45: R100354 | E45: Lindqvist, Aaliyah | F45: 1450 | G45: 1390 | H45: 1390 | I45: 46007 | J45: 46371 | L45: 0 | M45: 1 | N45: 205 | O45: Current/Notice/Vacant Residents
A46: B304 | B46: B2 | C46: 1046 | D46: R100361 | E46: Mbeki, Luis | F46: 1245 | G46: 1120 | H46: 1120 | I46: 45951 | J46: 46315 | L46: 0 | M46: 1 | N46: 0 | O46: Current/Notice/Vacant Residents
A47: C101 | B47: B2 | C47: 1038 | D47: R100368 | E47: Gutierrez, Rosa | F47: 1255 | G47: 1230 | H47: 1230 | I47: 45488 | J47: 46582 | L47: 0 | M47: 1 | N47: -147 | O47: Current/Notice/Vacant Residents
A48: C102 | B48: B1 | C48: 932 | D48: R100375 | E48: Okafor, Owen | F48: 1140 | G48: 1140 | H48: 1140 | I48: 45346 | J48: 46440 | L48: 0 | M48: 1 | N48: -5 | O48: Current/Notice/Vacant Residents
A49: C103 | B49: B1 | C49: 924 | D49: R100382 | E49: Dunmore, Ravi | F49: 1160 | G49: 1100 | H49: 1100 | I49: 45674 | J49: 46403 | L49: 0 | M49: 1 | N49: -207 | O49: Current/Notice/Vacant Residents
A50: C104 | B50: A1 | C50: 720 | D50: R100389 | E50: Zimmerman, Naomi | F50: 980 | G50: 900 | H50: 900 | I50: 46164 | J50: 46528 | L50: 75 | M50: 1 | N50: -18 | O50: Current/Notice/Vacant Residents
... A72: E102 | B72: A1 | C72: 706 | D72: R100543 | E72: Jernigan, Aaliyah | F72: 975 | G72: 975 | H72: 975 | I72: 45757 | J72: 46486 | L72: 0 | M72: 1 | N72: 1140 | O72: Current/Notice/Vacant Residents
A73: E103 | B73: A1 | C73: 706 | F73: 980 | G73: 0 | H73: 0 | K73: 46282 | L73: 0 | M73: 0 | N73: 40 | O73: Current/Notice/Vacant Residents
A74: E104 | B74: B1 | C74: 918 | D74: R100557 | E74: Okafor, Aaliyah | F74: 1160 | G74: 1135 | H74: 1135 | I74: 46080 | J74: 46444 | L74: 150 | M74: 1 | N74: -9 | O74: Current/Notice/Vacant Residents
A75: E201 | B75: B2 | C75: 1038 | D75: R100564 | E75: Zimmerman, Dante | F75: 1255 | G75: 1155 | H75: 1155 | I75: 45608 | J75: 46337 | L75: 0 | M75: 1 | N75: 10 | O75: Current/Notice/Vacant Residents
A76: E202 | B76: B2 | C76: 1032 | D76: R100571 | E76: Zimmerman, Jamal | F76: 1245 | G76: 1170 | H76: 1170 | I76: 46172 | J76: 46536 | L76: 35 | M76: 1 | N76: 1487 | O76: Current/Notice/Vacant Residents
A77: E203 | B77: A1 | C77: 712 | F77: 965 | G77: 0 | H77: 0 | K77: 46286 | L77: 0 | M77: 0 | N77: 5 | O77: Current/Notice/Vacant Residents
A78: E204 | B78: A1 | C78: 712 | D78: R100585 | E78: Yoder, Dante | F78: 980 | G78: 930 | H78: 930 | I78: 45921 | J78: 46650 | L78: 0 | M78: 1 | N78: 37 | O78: Current/Notice/Vacant Residents
A79: E301 | B79: B1 | C79: 918 | D79: R100592 | E79: Thatcher, Omar | F79: 1155 | G79: 1110 | H79: 1110 | I79: 46200 | J79: 46564 | L79: 0 | M79: 1 | N79: 1804 | O79: Current/Notice/Vacant Residents
A80: E302 | B80: B1 | C80: 924 | D80: R100599 | E80: Coleman, Tessa | F80: 1150 | G80: 1150 | H80: 1150 | I80: 45211 | J80: 46670 | L80: 35 | M80: 1 | N80: -257 | O80: Current/Notice/Vacant Residents
A81: E303 | B81: B1 | C81: 924 | D81: R100606 | E81: Castellano, Sofia | F81: 1160 | G81: 1125 | H81: 1125 | I81: 45420 | J81: 46514 | L81: 35 | M81: 1 | N81: -26 | O81: Current/Notice/Vacant Residents
A82: E304 | B82: B1 | C82: 932 | D82: R100613 | E82: Sandoval, Luis | F82: 1150 | G82: 1150 | H82: 1150 | I82: 45653 | J82: 46382 | L82: 0 | M82: 1 | N82: 23 | O82: Current/Notice/Vacant Residents
A83: F101 | B83: B2 | C83: 1038 | F83: 1255 | G83: 0 | H83: 0 | L83: 0 | M83: 0 | N83: 41 | O83: Current/Notice/Vacant Residents
A84: F102 | B84: A1 | C84: 712 | D84: R100627 | E84: Quill, Owen | F84: 975 | G84: 975 | H84: 975 | I84: 46263 | J84: 46627 | L84: 75 | M84: 1 | N84: -116 | O84: Current/Notice/Vacant Residents
A85: F103 | B85: C1 | C85: 1212 | D85: R100634 | E85: Fairchild, Isaiah | F85: 1440 | G85: 1295 | H85: 1295 | I85: 46018 | J85: 46382 | L85: 0 | M85: 1 | N85: -185 | O85: Current/Notice/Vacant Residents
A86: F104 | B86: C1 | C86: 1198 | D86: R100641 | E86: Underhill, Caleb | F86: 1460 | G86: 1385 | H86: 1385 | I86: 46257 | J86: 46621 | L86: 150 | M86: 1 | N86: -20 | O86: Current/Notice/Vacant Residents
A87: F201 | B87: A1 | C87: 712 | D87: R100648 | E87: Vasquez, Paige | F87: 980 | G87: 980 | H87: 980 | I87: 45734 | J87: 46463 | L87: 35 | M87: 1 | N87: -121 | O87: Current/Notice/Vacant Residents
A88: F202 | B88: C1 | C88: 1204 | D88: R100655 | E88: Underhill, Isaiah | F88: 1440 | G88: 1295 | H88: 1295 | I88: 45630 | J88: 46359 | L88: 150 | M88: 1 | N88: -69 | O88: Current/Notice/Vacant Residents
A89: F203 | B89: C1 | C89: 1198 | D89: R100662 | E89: Zimmerman, Imani | F89: 1450 | G89: 1405 | H89: 1405 | I89: 46122 | J89: 46486 | L89: 0 | M89: 1 | N89: -111 | O89: Current/Notice/Vacant Residents
A90: F204 | B90: A1 | C90: 712 | D90: R100669 | E90: Abernathy, Jamal | F90: 975 | G90: 915 | H90: 915 | I90: 45356 | J90: 46450 | L90: 0 | M90: 1 | N90: -231 | O90: Current/Notice/Vacant Residents
A91: F301 | B91: B2 | C91: 1032 | D91: R100676 | E91: Quill, Hannah | F91: 1255 | G91: 1230 | H91: 1230 | I91: 45292 | J91: 46386 | L91: 0 | M91: 1 | N91: 1487 | O91: Current/Notice/Vacant Residents
A92: F302 | B92: B2 | C92: 1038 | D92: R100683 | E92: Espinoza, Dante | F92: 1250 | G92: 1150 | H92: 1150 | I92: 46165 | J92: 46529 | L92: 0 | M92: 1 | N92: 64 | O92: Current/Notice/Vacant Residents
A93: F303 | B93: A1 | C93: 712 | D93: R100690 | E93: Nakamura, Marisol | F93: 975 | G93: 915 | H93: 915 | I93: 46238 | J93: 46602 | L93: 0 | M93: 1 | N93: 1675 | O93: Current/Notice/Vacant Residents
A94: F304 | B94: B1 | C94: 924 | D94: R100697 | E94: Abernathy, Tyrone | F94: 1150 | G94: 1090 | H94: 1090 | I94: 46153 | J94: 46517 | L94: 320 | M94: 1 | N94: 1605 | O94: Current/Notice/Vacant Residents
A95: G101 | B95: A1 | C95: 712 | D95: R100704 | E95: Iverson, Felix | F95: 965 | G95: 935 | H95: 935 | I95: 45894 | J95: 46623 | L95: 150 | M95: 1 | N95: -58 | O95: Current/Notice/Vacant Residents
... A99: G201 | B99: B2 | C99: 1046 | D99: R100732 | E99: Zimmerman, Felix | F99: 1235 | G99: 1200 | H99: 1200 | I99: 45916 | J99: 46645 | L99: 0 | M99: 1 | N99: 8 | O99: Current/Notice/Vacant Residents
A100: G202 | B100: B2 | C100: 1038 | F100: 1255 | G100: 0 | H100: 0 | L100: 0 | M100: 0 | N100: -134 | O100: Current/Notice/Vacant Residents
A101: G203 | B101: A1 | C101: 720 | D101: R100746 | E101: Dunmore, Jamal | F101: 975 | G101: 925 | H101: 925 | I101: 46007 | J101: 46371 | L101: 0 | M101: 1 | N101: 35 | O101: Current/Notice/Vacant Residents
A102: G204 | B102: B1 | C102: 924 | D102: R100753 | E102: Fairchild, Zane | F102: 1160 | G102: 1160 | H102: 1160 | I102: 46136 | J102: 46500 | L102: 0 | M102: 1 | N102: 24 | O102: Current/Notice/Vacant Residents
A103: G301 | B103: A1 | C103: 712 | D103: R100760 | E103: Abernathy, Felix | F103: 965 | G103: 945 | H103: 945 | I103: 45553 | J103: 46647 | L103: 0 | M103: 1 | N103: 95 | O103: Current/Notice/Vacant Residents
A104: G302 | B104: B2 | C104: 1038 | D104: R100767 | E104: Iverson, Owen | F104: 1250 | G104: 1125 | H104: 1125 | I104: 46218 | J104: 46582 | L104: 0 | M104: 1 | N104: -206 | O104: Current/Notice/Vacant Residents
A105: G303 | B105: B2 | C105: 1038 | D105: R100774 | E105: Rasmussen, Priya | F105: 1245 | G105: 1170 | H105: 1170 | I105: 45561 | J105: 46655 | L105: 0 | M105: 1 | N105: -88 | O105: Current/Notice/Vacant Residents
A106: G304 | B106: B2 | C106: 1046 | D106: R100781 | E106: Kowalski, Owen | F106: 1235 | G106: 1135 | H106: 1135 | I106: 45409 | J106: 46503 | L106: 0 | M106: 1 | N106: -98 | O106: Current/Notice/Vacant Residents
A107: H101 | B107: B1 | C107: 918 | D107: R100788 | E107: Coleman, Leah | F107: 1150 | G107: 1035 | H107: 1035 | I107: 45811 | J107: 46540 | L107: 0 | M107: 1 | N107: 5 | O107: Current/Notice/Vacant Residents
A108: H102 | B108: B1 | C108: 918 | D108: R100795 | E108: Jernigan, Zane | F108: 1150 | G108: 1150 | H108: 1150 | I108: 45939 | J108: 46668 | L108: 75 | M108: 1 | N108: 48 | O108: Current/Notice/Vacant Residents
A109: H103 | B109: B2 | C109: 1038 | D109: R100802 | E109: Gutierrez, Priya | F109: 1250 | G109: 1190 | H109: 1190 | I109: 45889 | J109: 46618 | L109: 0 | M109: 1 | N109: -37 | O109: Current/Notice/Vacant Residents
A110: H104 | B110: A1 | C110: 712 | D110: R100809 | E110: Rasmussen, Omar | F110: 985 | G110: 905 | H110: 905 | I110: 45641 | J110: 46370 | L110: 35 | M110: 1 | N110: -75 | O110: Current/Notice/Vacant Residents
A111: H201 | B111: B2 | C111: 1046 | D111: R100816 | E111: Mbeki, Tomas | F111: 1235 | G111: 1110 | H111: 1110 | I111: 45827 | J111: 46556 | L111: 0 | M111: 1 | N111: 89 | O111: Current/Notice/Vacant Residents
A112: H202 | B112: A1 | C112: 712 | D112: R100823 | E112: Lindqvist, Yolanda | F112: 985 | G112: 955 | H112: 955 | I112: 45236 | J112: 46330 | L112: 0 | M112: 1 | N112: -79 | O112: Current/Notice/Vacant Residents
A113: H203 | B113: A1 | C113: 712 | F113: 985 | G113: 0 | H113: 0 | K113: 46293 | L113: 0 | M113: 0 | N113: 94 | O113: Current/Notice/Vacant Residents
A114: H204 | B114: A1 | C114: 720 | D114: R100837 | E114: Whitlock, Elena | F114: 975 | G114: 895 | H114: 895 | I114: 45725 | J114: 46454 | L114: 0 | M114: 1 | N114: 1893 | O114: Current/Notice/Vacant Residents
A115: H301 | B115: B1 | C115: 932 | D115: R100844 | E115: Okafor, Hannah | F115: 1140 | G115: 1050 | H115: 1050 | I115: 46198 | J115: 46562 | L115: 0 | M115: 1 | N115: -5 | O115: Current/Notice/Vacant Residents
A116: H302 | B116: B1 | C116: 924 | D116: R100851 | E116: Lindqvist, Camila | F116: 1155 | G116: 1110 | H116: 1110 | I116: 45399 | J116: 46493 | L116: 0 | M116: 1 | N116: -166 | O116: Current/Notice/Vacant Residents
A117: H303 | B117: A1 | C117: 712 | D117: R100858 | E117: Coleman, Caleb | F117: 985 | G117: 955 | H117: 955 | I117: 45569 | J117: 46663 | L117: 0 | M117: 1 | N117: -4 | O117: Current/Notice/Vacant Residents
A118: H304 | B118: A1 | C118: 712 | D118: R100865 | E118: Gutierrez, Elena | F118: 975 | G118: 915 | H118: 915 | I118: 45368 | J118: 46462 | L118: 75 | M118: 1 | N118: 30 | O118: Current/Notice/Vacant Residents
N119: 75 | O119: Current/Notice/Vacant Residents
N120: -64 | O120: Current/Notice/Vacant Residents
N121: 33 | O121: Current/Notice/Vacant Residents
N122: 7 | O122: Current/Notice/Vacant Residents
N123: 1412 | O123: Current/Notice/Vacant Residents
N124: 50 | O124: Current/Notice/Vacant Residents
N125: 40 | O125: Current/Notice/Vacant Residents
N126: -27 | O126: Current/Notice/Vacant Residents
N127: 163 | O127: Current/Notice/Vacant Residents
N128: 1487 | O128: Current/Notice/Vacant Residents
N129: 176 | O129: Current/Notice/Vacant Residents
...

Sheet Unit Mix
A1: Unit Mix - Calculated from Rent Roll Detail
A2: =SUM(B6:B25) -> 96 | B2: =IFERROR(SUMPRODUCT(B6:B25,E6:E25)/SUM(B6:B25),0) -> 898.44583 | C2: =IFERROR(SUMPRODUCT(B6:B25,F6:F25)/SUM(B6:B25),0) -> 1136.8231 | D2: =IFERROR(SUMPRODUCT(B6:B25,G6:G25)/SUM(B6:B25),0) -> 1086.2173
A3: TOTAL UNITS | B3: BLENDED AVG SF | C3: BLENDED MKT RENT | D3: BLENDED IN-PLACE RENT
A5: Unit Type | B5: Units | C5: Occupied | D5: Vacant | E5: Avg SqFt | F5: Avg Market Rent | G5: Avg In-place Rent | H5: Monthly Market Rent | I5: Monthly In-place Rent | J5: How/Why: grouped from unit-level rent roll rows by unit type.
A6: A1 | B6: 36 | C6: 32 | D6: 4 | E6: 713.3 | F6: 975.97 | G6: 936.56 | H6: 35135 | I6: 29970 | J6: Calculated by grouping unit-level rent roll rows by unit type.
A7: B1 | B7: 30 | C7: 30 | D7: 0 | E7: 925 | F7: 1152.67 | G7: 1110.67 | H7: 34580 | I7: 33320 | J7: Calculated by grouping unit-level rent roll rows by unit type.
A8: B2 | B8: 20 | C8: 18 | D8: 2 | E8: 1039.5 | F8: 1245.75 | G8: 1172.78 | H8: 24915 | I8: 21110 | J8: Calculated by grouping unit-level rent roll rows by unit type.
A9: C1 | B9: 10 | C9: 10 | D9: 0 | E9: 1203.2 | F9: 1450.5 | G9: 1378.5 | H9: 14505 | I9: 13785 | J9: Calculated by grouping unit-level rent roll rows by unit type.
J10: Calculated by grouping unit-level rent roll rows; highlights unit-type rent gaps.
J11: Calculated by grouping unit-level rent roll rows; highlights unit-type rent gaps.
J12: Calculated by grouping unit-level rent roll rows; highlights unit-type rent gaps.
J13: Calculated by grouping unit-level rent roll rows; highlights unit-type rent gaps.
J14: Calculated by grouping unit-level rent roll rows; highlights unit-type rent gaps.
J15: Calculated by grouping unit-level rent roll rows; highlights unit-type rent gaps.
J16: Calculated by grouping unit-level rent roll rows; highlights unit-type rent gaps.
J17: Calculated by grouping unit-level rent roll rows; highlights unit-type rent gaps.
J18: Calculated by grouping unit-level rent roll rows; highlights unit-type rent gaps.
J19: Calculated by grouping unit-level rent roll rows; highlights unit-type rent gaps.
J20: Calculated by grouping unit-level rent roll rows; highlights unit-type rent gaps.

Sheet Tax
A1: Property Tax Forecast
A2: =B12 -> 165393 | B2: =B16 -> 183876 | C2: =B16-B12 -> 18482.996 | D2: =B9 -> 23.97
A3: CURRENT TAX | B3: NEW TAX AFTER SALE | C3: ANNUAL INCREASE | D3: MILLAGE RATE
A5: Metric | B5: Value | C5: Notes
A6: County PIN | B6: R72 00811 0006, R72 00811 0007 | C6: County / public tax record. Used to verify parcel.
A7: Site Address | B7: 4100 Millrace Pointe Drive, Dayton, OH 45415 | C7: County / public tax record. Used to confirm subject property.
A8: Current Taxable Value | B8: 6900000 | C8: County tax record / OM tax page. Current county taxable value.
A9: Current Millage Rate | B9: 23.97 | C9: County tax record / OM tax page. Ad valorem tax = taxable value x millage / 1,000 where applicable.
A10: Non-Ad Valorem Tax | B10: 0 | C10: County tax record / OM tax page. Added to ad valorem tax estimate.
A11: Current Ad Valorem Tax Estimate | B11: =IF(OR($B$8<=0,$B$9<=0),$B$13,$B$8*$B$9/1000) -> 165393 | C11: Calculated by model. Taxable value x millage / 1,000.
A12: Current Total Tax Estimate | B12: =IF(OR($B$8<=0,$B$9<=0),$B$13,$B$11+$B$10) -> 165393 | C12: Calculated by model. Ad valorem estimate + non-ad valorem.
A13: T12 Property Tax Expense | B13: 165400 | C13: T12 actuals. Displayed to compare T12 to county/OM tax estimate.
A14: Reassessment Basis After Sale | B14: =$B$8+('Debt & Exit'!$B$6-$B$8)*$B$19 -> 7671088.7 | C14: Calculated by model. Current taxable value plus the share of the step-up to purchase price allowed by the reassessment policy in B19. At 100% this equals the purchase price; at 0% it stays at today's taxable value.
A15: New Ad Valorem Tax After Sale | B15: =IF(OR($B$8<=0,$B$9<=0),$B$13,$B$14*$B$9/1000) -> 183876 | C15: Calculated by model. Reassessment basis x current millage / 1,000.
A16: New Year 1 Total Tax | B16: =IF(OR($B$8<=0,$B$9<=0),$B$13,$B$15+$B$10) -> 183876 | C16: Calculated by model. New ad valorem tax + non-ad valorem tax. With no millage on file it falls back to T12 tax grown one year.
A17: Annual Tax Growth | B17: =Inputs!$B$23 -> 0.03 | C17: Input link. Uses Inputs tax growth assumption.
A18: Tax Rule Note | B18: Reassessment on sale varies by state - set B19 accordingly. Some states reset to market value on a change of ownership (e.g. Florida non-homestead commercial, FS 193.1555): use 100%. Others do not - New Jersey bars reassessing a property solely because it sold (Township of West Milford v. Van Decker), so assessments move only on a district-wide revaluation: use 0% for the base case, or 100% together with the EQUALIZED value and the EFFECTIVE (equalized) millage to model a revaluation landing at market. If taxable value/millage are unavailable, the model uses actual T12 property tax grown by the tax-growth assumption instead of assuming $0. | C18: Confirm the rule for THIS jurisdiction before relying on Year 1 tax. The automated tax lookup writes its finding into B26.
A19: Reassessment on Sale (% of Price) | B19: 0.5 | C19: INPUT. 100% = assessment resets to the purchase price on sale. 0% = no reset; Year 1 tax holds at today's taxable value and only grows by the tax-growth assumption. Drives this tab AND every column of the Max Price Solver.
A21: Tax Forecast | B21: Year 1 | C21: Year 2 | D21: Year 3 | E21: Year 4 | F21: Year 5 | G21: Year 6 | H21: Year 7 | I21: Year 8 | J21: How/Why
A22: Property Tax | B22: =$B$16 -> 183876 | C22: =B22*(1+$B$17) -> 189392.28 | D22: =C22*(1+$B$17) -> 195074.04 | E22: =D22*(1+$B$17) -> 200926.27 | F22: =E22*(1+$B$17) -> 206954.05 | G22: =F22*(1+$B$17) -> 213162.68 | H22: =G22*(1+$B$17) -> 219557.56 | I22: =H22*(1+$B$17) -> 226144.28 | J22: Year 1 applies the reassessment policy in B19 to the purchase price, then grows by tax growth through Year 8. With no taxable value or millage on file it falls back to T12 tax grown forward.
A25: County source URL | B25: https://example.com/demo/montgomery-county-millage
A26: Tax rule/source URL | B26: Ohio re-appraises on a county cycle and a sale alone does not reset the assessment, but a school district can file a complaint citing the sale price; modeled as half the step-up to the purchase price. Values here are the appraised (market) value with the effective rate on it.

Sheet Reno Pace
A1: Renovation Pace - Monthly Ramp with Rent Downtime
A2: =Inputs!$B$30 -> 72 | B2: =Inputs!$B$45 -> 6 | C2: =IFERROR(B33,0) -> 0 | D2: =B38 -> 0
A3: UNITS TO RENOVATE | B3: PACE (UNITS/MO) | C3: YEAR 1 NET IMPACT | D3: STABILIZED PREMIUM/YR
A4: =IF($A$2=0,"No renovation program is modeled: Value-Add Units is 0 on the Inputs tab, so every month below is zero. Enter the number of units to renovate (and the pace) on Inputs to see the schedule.","Units completed monthly starting at the online start month. Renovations happen at lease turnover; each renovated unit is charged the downtime months of lost rent from Inputs.") -> Units completed monthly starting at the online start month. Renovations happen at lease turnover; each renovated unit is charged the downtime months of lost rent from Inputs.
A5: Month | B5: Units Completed This Month | C5: Units Under Renovation | D5: Cumulative Units Online | E5: Monthly Rent Premium | F5: Rent Downtime (downtime months x avg rent) | G5: Net Monthly Impact
A6: 1 | B6: =IF(A6<Inputs!$B$33,0,MAX(0,MIN(Inputs!$B$45,Inputs!$B$30-SUM($B$5:B5)))) -> 0 | C6: =SUMIFS($B$6:$B$101,$A$6:$A$101,">"&A6,$A$6:$A$101,"<="&A6+Inputs!$B$32) -> 0 | D6: =SUM($B$6:B6) -> 0 | E6: =D6*Inputs!$B$31 -> 0 | F6: =IFERROR(B6*('Rent Roll'!$B$16/Inputs!$B$13)*Inputs!$B$32,0) -> 0 | G6: =E6-F6 -> 0
A7: 2 | B7: =IF(A7<Inputs!$B$33,0,MAX(0,MIN(Inputs!$B$45,Inputs!$B$30-SUM($B$5:B6)))) -> 0 | C7: =SUMIFS($B$6:$B$101,$A$6:$A$101,">"&A7,$A$6:$A$101,"<="&A7+Inputs!$B$32) -> 6 | D7: =SUM($B$6:B7) -> 0 | E7: =D7*Inputs!$B$31 -> 0 | F7: =IFERROR(B7*('Rent Roll'!$B$16/Inputs!$B$13)*Inputs!$B$32,0) -> 0 | G7: =E7-F7 -> 0
A8: 3 | B8: =IF(A8<Inputs!$B$33,0,MAX(0,MIN(Inputs!$B$45,Inputs!$B$30-SUM($B$5:B7)))) -> 6 | C8: =SUMIFS($B$6:$B$101,$A$6:$A$101,">"&A8,$A$6:$A$101,"<="&A8+Inputs!$B$32) -> 6 | D8: =SUM($B$6:B8) -> 6 | E8: =D8*Inputs!$B$31 -> 1020 | F8: =IFERROR(B8*('Rent Roll'!$B$16/Inputs!$B$13)*Inputs!$B$32,0) -> 6136.5625 | G8: =E8-F8 -> -5116.5625
A9: 4 | B9: =IF(A9<Inputs!$B$33,0,MAX(0,MIN(Inputs!$B$45,Inputs!$B$30-SUM($B$5:B8)))) -> 6 | C9: =SUMIFS($B$6:$B$101,$A$6:$A$101,">"&A9,$A$6:$A$101,"<="&A9+Inputs!$B$32) -> 6 | D9: =SUM($B$6:B9) -> 12 | E9: =D9*Inputs!$B$31 -> 2040 | F9: =IFERROR(B9*('Rent Roll'!$B$16/Inputs!$B$13)*Inputs!$B$32,0) -> 6136.5625 | G9: =E9-F9 -> -4096.5625
A10: 5 | B10: =IF(A10<Inputs!$B$33,0,MAX(0,MIN(Inputs!$B$45,Inputs!$B$30-SUM($B$5:B9)))) -> 6 | C10: =SUMIFS($B$6:$B$101,$A$6:$A$101,">"&A10,$A$6:$A$101,"<="&A10+Inputs!$B$32) -> 6 | D10: =SUM($B$6:B10) -> 18 | E10: =D10*Inputs!$B$31 -> 3060 | F10: =IFERROR(B10*('Rent Roll'!$B$16/Inputs!$B$13)*Inputs!$B$32,0) -> 6136.5625 | G10: =E10-F10 -> -3076.5625
A11: 6 | B11: =IF(A11<Inputs!$B$33,0,MAX(0,MIN(Inputs!$B$45,Inputs!$B$30-SUM($B$5:B10)))) -> 6 | C11: =SUMIFS($B$6:$B$101,$A$6:$A$101,">"&A11,$A$6:$A$101,"<="&A11+Inputs!$B$32) -> 6 | D11: =SUM($B$6:B11) -> 24 | E11: =D11*Inputs!$B$31 -> 4080 | F11: =IFERROR(B11*('Rent Roll'!$B$16/Inputs!$B$13)*Inputs!$B$32,0) -> 6136.5625 | G11: =E11-F11 -> -2056.5625
A12: 7 | B12: =IF(A12<Inputs!$B$33,0,MAX(0,MIN(Inputs!$B$45,Inputs!$B$30-SUM($B$5:B11)))) -> 6 | C12: =SUMIFS($B$6:$B$101,$A$6:$A$101,">"&A12,$A$6:$A$101,"<="&A12+Inputs!$B$32) -> 6 | D12: =SUM($B$6:B12) -> 30 | E12: =D12*Inputs!$B$31 -> 5100 | F12: =IFERROR(B12*('Rent Roll'!$B$16/Inputs!$B$13)*Inputs!$B$32,0) -> 6136.5625 | G12: =E12-F12 -> -1036.5625
A13: 8 | B13: =IF(A13<Inputs!$B$33,0,MAX(0,MIN(Inputs!$B$45,Inputs!$B$30-SUM($B$5:B12)))) -> 6 | C13: =SUMIFS($B$6:$B$101,$A$6:$A$101,">"&A13,$A$6:$A$101,"<="&A13+Inputs!$B$32) -> 6 | D13: =SUM($B$6:B13) -> 36 | E13: =D13*Inputs!$B$31 -> 6120 | F13: =IFERROR(B13*('Rent Roll'!$B$16/Inputs!$B$13)*Inputs!$B$32,0) -> 6136.5625 | G13: =E13-F13 -> -16.5625
A14: 9 | B14: =IF(A14<Inputs!$B$33,0,MAX(0,MIN(Inputs!$B$45,Inputs!$B$30-SUM($B$5:B13)))) -> 6 | C14: =SUMIFS($B$6:$B$101,$A$6:$A$101,">"&A14,$A$6:$A$101,"<="&A14+Inputs!$B$32) -> 6 | D14: =SUM($B$6:B14) -> 42 | E14: =D14*Inputs!$B$31 -> 7140 | F14: =IFERROR(B14*('Rent Roll'!$B$16/Inputs!$B$13)*Inputs!$B$32,0) -> 6136.5625 | G14: =E14-F14 -> 1003.4375
A15: 10 | B15: =IF(A15<Inputs!$B$33,0,MAX(0,MIN(Inputs!$B$45,Inputs!$B$30-SUM($B$5:B14)))) -> 6 | C15: =SUMIFS($B$6:$B$101,$A$6:$A$101,">"&A15,$A$6:$A$101,"<="&A15+Inputs!$B$32) -> 6 | D15: =SUM($B$6:B15) -> 48 | E15: =D15*Inputs!$B$31 -> 8160 | F15: =IFERROR(B15*('Rent Roll'!$B$16/Inputs!$B$13)*Inputs!$B$32,0) -> 6136.5625 | G15: =E15-F15 -> 2023.4375
A16: 11 | B16: =IF(A16<Inputs!$B$33,0,MAX(0,MIN(Inputs!$B$45,Inputs!$B$30-SUM($B$5:B15)))) -> 6 | C16: =SUMIFS($B$6:$B$101,$A$6:$A$101,">"&A16,$A$6:$A$101,"<="&A16+Inputs!$B$32) -> 6 | D16: =SUM($B$6:B16) -> 54 | E16: =D16*Inputs!$B$31 -> 9180 | F16: =IFERROR(B16*('Rent Roll'!$B$16/Inputs!$B$13)*Inputs!$B$32,0) -> 6136.5625 | G16: =E16-F16 -> 3043.4375
A17: 12 | B17: =IF(A17<Inputs!$B$33,0,MAX(0,MIN(Inputs!$B$45,Inputs!$B$30-SUM($B$5:B16)))) -> 6 | C17: =SUMIFS($B$6:$B$101,$A$6:$A$101,">"&A17,$A$6:$A$101,"<="&A17+Inputs!$B$32) -> 6 | D17: =SUM($B$6:B17) -> 60 | E17: =D17*Inputs!$B$31 -> 10200 | F17: =IFERROR(B17*('Rent Roll'!$B$16/Inputs!$B$13)*Inputs!$B$32,0) -> 6136.5625 | G17: =E17-F17 -> 4063.4375
... A101: 96 | B101: =IF(A101<Inputs!$B$33,0,MAX(0,MIN(Inputs!$B$45,Inputs!$B$30-SUM($B$5:B100)))) -> 0 | C101: =SUMIFS($B$6:$B$101,$A$6:$A$101,">"&A101,$A$6:$A$101,"<="&A101+Inputs!$B$32) -> 0 | D101: =SUM($B$6:B101) -> 72 | E101: =D101*Inputs!$B$31 -> 12240 | F101: =IFERROR(B101*('Rent Roll'!$B$16/Inputs!$B$13)*Inputs!$B$32,0) -> 0 | G101: =E101-F101 -> 12240
A103: Renovation Schedule Summary - months 1-96 | B103: Net impact | C103: Gross premium | D103: Downtime charged | E103: Units online at year end
A104: Year 1 Net Rent Impact | B104: =SUM(G6:G17) -> -5265.625 | C104: =SUM(E6:E17) -> 56100 | D104: =SUM(F6:F17) -> 61365.625 | E104: =D17 -> 60
A105: Year 2 Net Rent Impact | B105: =SUM(G18:G29) -> 133586.88 | C105: =SUM(E18:E29) -> 145860 | D105: =SUM(F18:F29) -> 12273.125 | E105: =D29 -> 72
A106: Year 3 Net Rent Impact | B106: =SUM(G30:G41) -> 146880 | C106: =SUM(E30:E41) -> 146880 | D106: =SUM(F30:F41) -> 0 | E106: =D41 -> 72
A107: Year 4 Net Rent Impact | B107: =SUM(G42:G53) -> 146880 | C107: =SUM(E42:E53) -> 146880 | D107: =SUM(F42:F53) -> 0 | E107: =D53 -> 72
A108: Year 5 Net Rent Impact | B108: =SUM(G54:G65) -> 146880 | C108: =SUM(E54:E65) -> 146880 | D108: =SUM(F54:F65) -> 0 | E108: =D65 -> 72
A109: Year 6 Net Rent Impact | B109: =SUM(G66:G77) -> 146880 | C109: =SUM(E66:E77) -> 146880 | D109: =SUM(F66:F77) -> 0 | E109: =D77 -> 72
A110: Year 7 Net Rent Impact | B110: =SUM(G78:G89) -> 146880 | C110: =SUM(E78:E89) -> 146880 | D110: =SUM(F78:F89) -> 0 | E110: =D89 -> 72
A111: Year 8 Net Rent Impact | B111: =SUM(G90:G101) -> 146880 | C111: =SUM(E90:E101) -> 146880 | D111: =SUM(F90:F101) -> 0 | E111: =D101 -> 72
A113: Months to complete the programme | B113: =IFERROR(MATCH(Inputs!$B$30,$D$6:$D$101,0),"more than 96") -> 14
A114: Stabilised annual gross premium (reference) | B114: =Inputs!$B$30*Inputs!$B$31*12 -> 146880
A115: Year 1 rent downtime | B115: =SUM(F6:F17) -> 61365.625
A116: Total rent downtime, Years 1-8 | B116: =SUM(F6:F101) -> 73638.75
A118: Each pro forma year now reads its own 12 months from the schedule above, so a slower pace genuinely delays the premium and keeps charging downtime while units are offline. If 'months to complete' exceeds the hold period, the programme never finishes inside the model and the exit NOI reflects that.

Sheet Pro Forma
A1: Eight-Year Pro Forma - Company Underwriting Case
A2: =D30 -> 484834.88 | B2: =K30 -> 843140.9 | C2: =D36 -> 0.043550959 | D2: =E36 -> 0.10061883
A3: YEAR 1 NOI | B3: YEAR 8 NOI | C3: YEAR 1 CASH-ON-CASH | D3: YEAR 2 CASH-ON-CASH
A4: Benchmark column sits at the right, just past Year 8: OUR number in $ per unit per YEAR. Blank = the model uses the T12-based figure. Enter a value and that line switches to benchmark x units from Year 1 on, then grows with expense growth. Turnover is the exception: it is entered on Inputs as $ per TURNED unit and converted here.
A5: Line Item | B5: T12 / Source | C5: T12 $/Unit/Mo | D5: Year 1 | E5: Year 2 | F5: Year 3 | G5: Year 4 | H5: Year 5 | I5: Year 6 | J5: Year 7 | K5: Year 8 | M5: Benchmark ($/Unit/Yr) | N5: Yr-1 $ / Unit | O5: Yr-1 % of EGI
A6: Base Gross Potential Rent | B6: ='T12 Actuals'!$B$6 -> 1305600 | C6: =IFERROR(B6/Units/12,0) -> 1133.3333 | D6: =('Rent Roll'!$B$16*12)+('Rent Roll'!$B$15*12-'Rent Roll'!$B$16*12)*Inputs!$B$44 -> 1243920 | E6: =('Rent Roll'!$B$15*12)*(1+Inputs!$B$21) -> 1348908.6 | F6: =E6*(1+Inputs!$B$21) -> 1389375.9 | G6: =F6*(1+Inputs!$B$21) -> 1431057.1 | H6: =G6*(1+Inputs!$B$21) -> 1473988.8 | I6: =H6*(1+Inputs!$B$21) -> 1518208.5 | J6: =I6*(1+Inputs!$B$21) -> 1563754.8 | K6: =J6*(1+Inputs!$B$21) -> 1610667.4 | N6: =IFERROR($E6/Inputs!$B$13,"") -> 14051.131 | O6: =IFERROR($E6/$E$15,"") -> 0.91570244
A7: Value-Add Rent Impact, Net of Downtime | B7: 0 | C7: =IFERROR(B7/Units/12,0) -> 0 | D7: ='Reno Pace'!$B$104 -> -5265.625 | E7: ='Reno Pace'!$B$105 -> 133586.88 | F7: ='Reno Pace'!$B$106*(1+Inputs!$B$21) -> 151286.4 | G7: ='Reno Pace'!$B$107*(1+Inputs!$B$21)^2 -> 155824.99 | H7: ='Reno Pace'!$B$108*(1+Inputs!$B$21)^3 -> 160499.74 | I7: ='Reno Pace'!$B$109*(1+Inputs!$B$21)^4 -> 165314.73 | J7: ='Reno Pace'!$B$110*(1+Inputs!$B$21)^5 -> 170274.18 | K7: ='Reno Pace'!$B$111*(1+Inputs!$B$21)^6 -> 175382.4 | N7: =IFERROR($E7/Inputs!$B$13,"") -> 1391.5299 | O7: =IFERROR($E7/$E$15,"") -> 0.090685038
A8: Adjusted Gross Potential Rent | B8: =B6+B7 -> 1305600 | C8: =IFERROR(B8/Units/12,0) -> 1133.3333 | D8: =D6+D7 -> 1238654.4 | E8: =E6+E7 -> 1482495.5 | F8: =F6+F7 -> 1540662.3 | G8: =G6+G7 -> 1586882.1 | H8: =H6+H7 -> 1634488.6 | I8: =I6+I7 -> 1683523.2 | J8: =J6+J7 -> 1734028.9 | K8: =K6+K7 -> 1786049.8 | N8: =IFERROR($E8/Inputs!$B$13,"") -> 15442.661 | O8: =IFERROR($E8/$E$15,"") -> 1.0063875
A9: Vacancy % Assumed (1 - stabilized occupancy target) | B9: =Inputs!$B$25 -> 0.0625 | D9: =1-StabilizedOccupancyTarget -> 0.04 | E9: =1-StabilizedOccupancyTarget -> 0.04 | F9: =1-StabilizedOccupancyTarget -> 0.04 | G9: =1-StabilizedOccupancyTarget -> 0.04 | H9: =1-StabilizedOccupancyTarget -> 0.04 | I9: =1-StabilizedOccupancyTarget -> 0.04 | J9: =1-StabilizedOccupancyTarget -> 0.04 | K9: =1-StabilizedOccupancyTarget -> 0.04
A10: Vacancy Loss | B10: ='T12 Actuals'!$B$24 -> -84900 | C10: =IFERROR(B10/Units/12,0) -> -73.697917 | D10: =-D8*D9 -> -49546.175 | E10: =-E8*E9 -> -59299.819 | F10: =-F8*F9 -> -61626.49 | G10: =-G8*G9 -> -63475.285 | H10: =-H8*H9 -> -65379.544 | I10: =-I8*I9 -> -67340.93 | J10: =-J8*J9 -> -69361.158 | K10: =-K8*K9 -> -71441.993 | N10: =IFERROR($E10/Inputs!$B$13,"") -> -617.70645 | O10: =IFERROR($E10/$E$15,"") -> -0.040255499
A11: Bad Debt | B11: ='T12 Actuals'!$B$25 -> -12400 | C11: =IFERROR(B11/Units/12,0) -> -10.763889 | D11: =-D8*Inputs!$B$24 -> -24773.088 | E11: =-E8*Inputs!$B$24 -> -29649.91 | F11: =-F8*Inputs!$B$24 -> -30813.245 | G11: =-G8*Inputs!$B$24 -> -31737.643 | H11: =-H8*Inputs!$B$24 -> -32689.772 | I11: =-I8*Inputs!$B$24 -> -33670.465 | J11: =-J8*Inputs!$B$24 -> -34680.579 | K11: =-K8*Inputs!$B$24 -> -35720.996 | N11: =IFERROR($E11/Inputs!$B$13,"") -> -308.85322 | O11: =IFERROR($E11/$E$15,"") -> -0.02012775
A12: Other Rental Deductions / Concessions | B12: ='T12 Actuals'!$B$26 -> -11800 | C12: =IFERROR(B12/Units/12,0) -> -10.243056 | D12: =-Inputs!$B$29 -> -17433.333 | E12: =D12*(1+Inputs!$B$21) -> -17956.333 | F12: =E12*(1+Inputs!$B$21) -> -18495.023 | G12: =F12*(1+Inputs!$B$21) -> -19049.874 | H12: =G12*(1+Inputs!$B$21) -> -19621.37 | I12: =H12*(1+Inputs!$B$21) -> -20210.011 | J12: =I12*(1+Inputs!$B$21) -> -20816.312 | K12: =J12*(1+Inputs!$B$21) -> -21440.801 | N12: =IFERROR($E12/Inputs!$B$13,"") -> -187.04514 | O12: =IFERROR($E12/$E$15,"") -> -0.012189602
A13: Net Rental Income | B13: ='T12 Actuals'!$B$8 -> 1139100 | C13: =IFERROR(B13/Units/12,0) -> 988.80208 | D13: =SUM(D8:D12) -> 1146901.8 | E13: =SUM(E8:E12) -> 1375589.5 | F13: =SUM(F8:F12) -> 1429727.5 | G13: =SUM(G8:G12) -> 1472619.4 | H13: =SUM(H8:H12) -> 1516797.9 | I13: =SUM(I8:I12) -> 1562301.9 | J13: =SUM(J8:J12) -> 1609170.9 | K13: =SUM(K8:K12) -> 1657446.1 | N13: =IFERROR($E13/Inputs!$B$13,"") -> 14329.057 | O13: =IFERROR($E13/$E$15,"") -> 0.93381466
A14: Other Income | B14: ='T12 Actuals'!$B$9 -> 91900 | C14: =IFERROR(B14/Units/12,0) -> 79.774306 | D14: =(B14+AdditionalOtherIncome)*(1+Inputs!$B$21) -> 94657 | E14: =D14*(1+Inputs!$B$21) -> 97496.71 | F14: =E14*(1+Inputs!$B$21) -> 100421.61 | G14: =F14*(1+Inputs!$B$21) -> 103434.26 | H14: =G14*(1+Inputs!$B$21) -> 106537.29 | I14: =H14*(1+Inputs!$B$21) -> 109733.41 | J14: =I14*(1+Inputs!$B$21) -> 113025.41 | K14: =J14*(1+Inputs!$B$21) -> 116416.17 | N14: =IFERROR($E14/Inputs!$B$13,"") -> 1015.5907 | O14: =IFERROR($E14/$E$15,"") -> 0.066185341
A15: Effective Gross Income | B15: ='T12 Actuals'!$B$10 -> 1231000 | C15: =IFERROR(B15/Units/12,0) -> 1068.5764 | D15: =D13+D14 -> 1241558.8 | E15: =E13+E14 -> 1473086.2 | F15: =F13+F14 -> 1530149.2 | G15: =G13+G14 -> 1576053.6 | H15: =H13+H14 -> 1623335.2 | I15: =I13+I14 -> 1672035.3 | J15: =J13+J14 -> 1722196.3 | K15: =K13+K14 -> 1773862.2 | N15: =IFERROR($E15/Inputs!$B$13,"") -> 15344.648 | O15: =IFERROR($E15/$E$15,"") -> 1
A16: Repairs & Maintenance | B16: ='T12 Actuals'!$B$11 -> 70700 | C16: =IFERROR(B16/Units/12,0) -> 61.371528 | D16: =IF($M16>0,$M16*Units,B16*(1+Inputs!$B$22)) -> 72000 | E16: =D16*(1+Inputs!$B$22) -> 74160 | F16: =E16*(1+Inputs!$B$22) -> 76384.8 | G16: =F16*(1+Inputs!$B$22) -> 78676.344 | H16: =G16*(1+Inputs!$B$22) -> 81036.634 | I16: =H16*(1+Inputs!$B$22) -> 83467.733 | J16: =I16*(1+Inputs!$B$22) -> 85971.765 | K16: =J16*(1+Inputs!$B$22) -> 88550.918 | M16: 750 | N16: =IFERROR($E16/Inputs!$B$13,"") -> 772.5 | O16: =IFERROR($E16/$E$15,"") -> 0.050343287
A17: Turnover Costs | B17: ='T12 Actuals'!$B$12 -> 26600 | C17: =IFERROR(B17/Units/12,0) -> 23.090278 | D17: =IF($M17>0,$M17*Units,B17*(1+Inputs!$B$22)) -> 10560 | E17: =D17*(1+Inputs!$B$22) -> 10876.8 | F17: =E17*(1+Inputs!$B$22) -> 11203.104 | G17: =F17*(1+Inputs!$B$22) -> 11539.197 | H17: =G17*(1+Inputs!$B$22) -> 11885.373 | I17: =H17*(1+Inputs!$B$22) -> 12241.934 | J17: =I17*(1+Inputs!$B$22) -> 12609.192 | K17: =J17*(1+Inputs!$B$22) -> 12987.468 | M17: =Inputs!$B$53*Inputs!$B$50 -> 110 | N17: =IFERROR($E17/Inputs!$B$13,"") -> 113.3 | O17: =IFERROR($E17/$E$15,"") -> 0.0073836821
A18: Labor Costs (Payroll) | B18: ='T12 Actuals'!$B$13 -> 123000 | C18: =IFERROR(B18/Units/12,0) -> 106.77083 | D18: =IF($M18>0,$M18*Units,B18*(1+Inputs!$B$22)) -> 120000 | E18: =D18*(1+Inputs!$B$22) -> 123600 | F18: =E18*(1+Inputs!$B$22) -> 127308 | G18: =F18*(1+Inputs!$B$22) -> 131127.24 | H18: =G18*(1+Inputs!$B$22) -> 135061.06 | I18: =H18*(1+Inputs!$B$22) -> 139112.89 | J18: =I18*(1+Inputs!$B$22) -> 143286.28 | K18: =J18*(1+Inputs!$B$22) -> 147584.86 | M18: 1250 | N18: =IFERROR($E18/Inputs!$B$13,"") -> 1287.5 | O18: =IFERROR($E18/$E$15,"") -> 0.083905479
A19: Advertising & Promotions | B19: ='T12 Actuals'!$B$14 -> 15800 | C19: =IFERROR(B19/Units/12,0) -> 13.715278 | D19: =IF($M19>0,$M19*Units,B19*(1+Inputs!$B$22)) -> 16274 | E19: =D19*(1+Inputs!$B$22) -> 16762.22 | F19: =E19*(1+Inputs!$B$22) -> 17265.087 | G19: =F19*(1+Inputs!$B$22) -> 17783.039 | H19: =G19*(1+Inputs!$B$22) -> 18316.53 | I19: =H19*(1+Inputs!$B$22) -> 18866.026 | J19: =I19*(1+Inputs!$B$22) -> 19432.007 | K19: =J19*(1+Inputs!$B$22) -> 20014.967 | N19: =IFERROR($E19/Inputs!$B$13,"") -> 174.60646 | O19: =IFERROR($E19/$E$15,"") -> 0.011378981
A20: General & Administrative | B20: ='T12 Actuals'!$B$15 -> 27700 | C20: =IFERROR(B20/Units/12,0) -> 24.045139 | D20: =IF($M20>0,$M20*Units,B20*(1+Inputs!$B$22)) -> 28531 | E20: =D20*(1+Inputs!$B$22) -> 29386.93 | F20: =E20*(1+Inputs!$B$22) -> 30268.538 | G20: =F20*(1+Inputs!$B$22) -> 31176.594 | H20: =G20*(1+Inputs!$B$22) -> 32111.892 | I20: =H20*(1+Inputs!$B$22) -> 33075.249 | J20: =I20*(1+Inputs!$B$22) -> 34067.506 | K20: =J20*(1+Inputs!$B$22) -> 35089.531 | N20: =IFERROR($E20/Inputs!$B$13,"") -> 306.11385 | O20: =IFERROR($E20/$E$15,"") -> 0.019949227
A21: Other Controllable (unallocated) | B21: ='T12 Actuals'!$B$16-SUM(B16:B20) -> 0 | C21: =IFERROR(B21/Units/12,0) -> 0 | D21: =B21*(1+Inputs!$B$22) -> 0 | E21: =D21*(1+Inputs!$B$22) -> 0 | F21: =E21*(1+Inputs!$B$22) -> 0 | G21: =F21*(1+Inputs!$B$22) -> 0 | H21: =G21*(1+Inputs!$B$22) -> 0 | I21: =H21*(1+Inputs!$B$22) -> 0 | J21: =I21*(1+Inputs!$B$22) -> 0 | K21: =J21*(1+Inputs!$B$22) -> 0 | N21: =IFERROR($E21/Inputs!$B$13,"") -> 0 | O21: =IFERROR($E21/$E$15,"") -> 0
A22: Utility Costs | B22: ='T12 Actuals'!$B$17 -> 121500 | C22: =IFERROR(B22/Units/12,0) -> 105.46875 | D22: =IF($M22>0,$M22*Units,B22*(1+Inputs!$B$22)) -> 125145 | E22: =D22*(1+Inputs!$B$22) -> 128899.35 | F22: =E22*(1+Inputs!$B$22) -> 132766.33 | G22: =F22*(1+Inputs!$B$22) -> 136749.32 | H22: =G22*(1+Inputs!$B$22) -> 140851.8 | I22: =H22*(1+Inputs!$B$22) -> 145077.35 | J22: =I22*(1+Inputs!$B$22) -> 149429.67 | K22: =J22*(1+Inputs!$B$22) -> 153912.56 | N22: =IFERROR($E22/Inputs!$B$13,"") -> 1342.7016 | O22: =IFERROR($E22/$E$15,"") -> 0.087502926
A23: Insurance and Bonds | B23: ='T12 Actuals'!$B$19 -> 91800 | C23: =IFERROR(B23/Units/12,0) -> 79.6875 | D23: =IF($M23>0,$M23*Units,B23*(1+Inputs!$B$22)) -> 105600 | E23: =D23*(1+Inputs!$B$22) -> 108768 | F23: =E23*(1+Inputs!$B$22) -> 112031.04 | G23: =F23*(1+Inputs!$B$22) -> 115391.97 | H23: =G23*(1+Inputs!$B$22) -> 118853.73 | I23: =H23*(1+Inputs!$B$22) -> 122419.34 | J23: =I23*(1+Inputs!$B$22) -> 126091.92 | K23: =J23*(1+Inputs!$B$22) -> 129874.68 | M23: 1100 | N23: =IFERROR($E23/Inputs!$B$13,"") -> 1133 | O23: =IFERROR($E23/$E$15,"") -> 0.073836821
A24: Property Taxes | B24: ='T12 Actuals'!$B$20 -> 165400 | C24: =IFERROR(B24/Units/12,0) -> 143.57639 | D24: =IF($M24>0,$M24*Units,Tax!$B$22) -> 183876 | E24: =IF($M24>0,D24*(1+Inputs!$B$23),Tax!$C$22) -> 189392.28 | F24: =IF($M24>0,E24*(1+Inputs!$B$23),Tax!$D$22) -> 195074.04 | G24: =IF($M24>0,F24*(1+Inputs!$B$23),Tax!$E$22) -> 200926.27 | H24: =IF($M24>0,G24*(1+Inputs!$B$23),Tax!$F$22) -> 206954.05 | I24: =IF($M24>0,H24*(1+Inputs!$B$23),Tax!$G$22) -> 213162.68 | J24: =IF($M24>0,I24*(1+Inputs!$B$23),Tax!$H$22) -> 219557.56 | K24: =IF($M24>0,J24*(1+Inputs!$B$23),Tax!$I$22) -> 226144.28 | N24: =IFERROR($E24/Inputs!$B$13,"") -> 1972.8362 | O24: =IFERROR($E24/$E$15,"") -> 0.12856836
A25: Other Property Expenses | B25: ='T12 Actuals'!$B$21 -> 22000 | C25: =IFERROR(B25/Units/12,0) -> 19.097222 | D25: =IF($M25>0,$M25*Units,B25*(1+Inputs!$B$22)) -> 22660 | E25: =D25*(1+Inputs!$B$22) -> 23339.8 | F25: =E25*(1+Inputs!$B$22) -> 24039.994 | G25: =F25*(1+Inputs!$B$22) -> 24761.194 | H25: =G25*(1+Inputs!$B$22) -> 25504.03 | I25: =H25*(1+Inputs!$B$22) -> 26269.151 | J25: =I25*(1+Inputs!$B$22) -> 27057.225 | K25: =J25*(1+Inputs!$B$22) -> 27868.942 | N25: =IFERROR($E25/Inputs!$B$13,"") -> 243.12292 | O25: =IFERROR($E25/$E$15,"") -> 0.015844151
A26: Miscellaneous Expense (One-Time, Yr 1) | B26: 0 | C26: =IFERROR(B26/Units/12,0) -> 0 | D26: =Inputs!$B$37 -> 10000 | E26: =0 -> 0 | F26: =0 -> 0 | G26: =0 -> 0 | H26: =0 -> 0 | I26: =0 -> 0 | J26: =0 -> 0 | K26: =0 -> 0 | N26: =IFERROR($E26/Inputs!$B$13,"") -> 0 | O26: =IFERROR($E26/$E$15,"") -> 0
A27: Management Fee | B27: ='T12 Actuals'!$B$18 -> 43085 | C27: =IFERROR(B27/Units/12,0) -> 37.400174 | D27: =IF($M27>0,$M27*Units,D15*Inputs!$B$27) -> 37246.765 | E27: =IF($M27>0,D27*(1+Inputs!$B$22),E15*Inputs!$B$27) -> 44192.585 | F27: =IF($M27>0,E27*(1+Inputs!$B$22),F15*Inputs!$B$27) -> 45904.475 | G27: =IF($M27>0,F27*(1+Inputs!$B$22),G15*Inputs!$B$27) -> 47281.609 | H27: =IF($M27>0,G27*(1+Inputs!$B$22),H15*Inputs!$B$27) -> 48700.057 | I27: =IF($M27>0,H27*(1+Inputs!$B$22),I15*Inputs!$B$27) -> 50161.059 | J27: =IF($M27>0,I27*(1+Inputs!$B$22),J15*Inputs!$B$27) -> 51665.89 | K27: =IF($M27>0,J27*(1+Inputs!$B$22),K15*Inputs!$B$27) -> 53215.867 | N27: =IFERROR($E27/Inputs!$B$13,"") -> 460.33943 | O27: =IFERROR($E27/$E$15,"") -> 0.03
A28: Asset Management Fee | B28: 0 | C28: =IFERROR(B28/Units/12,0) -> 0 | D28: =IF($M28>0,$M28*Units,D15*Inputs!$B$28) -> 24831.176 | E28: =IF($M28>0,D28*(1+Inputs!$B$22),E15*Inputs!$B$28) -> 29461.723 | F28: =IF($M28>0,E28*(1+Inputs!$B$22),F15*Inputs!$B$28) -> 30602.983 | G28: =IF($M28>0,F28*(1+Inputs!$B$22),G15*Inputs!$B$28) -> 31521.072 | H28: =IF($M28>0,G28*(1+Inputs!$B$22),H15*Inputs!$B$28) -> 32466.705 | I28: =IF($M28>0,H28*(1+Inputs!$B$22),I15*Inputs!$B$28) -> 33440.706 | J28: =IF($M28>0,I28*(1+Inputs!$B$22),J15*Inputs!$B$28) -> 34443.927 | K28: =IF($M28>0,J28*(1+Inputs!$B$22),K15*Inputs!$B$28) -> 35477.245 | N28: =IFERROR($E28/Inputs!$B$13,"") -> 306.89295 | O28: =IFERROR($E28/$E$15,"") -> 0.02
A29: Total Operating Expenses | B29: ='T12 Actuals'!$B$22 -> 707585 | C29: =IFERROR(B29/Units/12,0) -> 614.22309 | D29: =SUM(D16:D28) -> 756723.94 | E29: =SUM(E16:E28) -> 778839.68 | F29: =SUM(F16:F28) -> 802848.4 | G29: =SUM(G16:G28) -> 826933.85 | H29: =SUM(H16:H28) -> 851741.86 | I29: =SUM(I16:I28) -> 877294.12 | J29: =SUM(J16:J28) -> 903612.94 | K29: =SUM(K16:K28) -> 930721.33 | N29: =IFERROR($E29/Inputs!$B$13,"") -> 8112.9134 | O29: =IFERROR($E29/$E$15,"") -> 0.52871292
A30: Net Operating Income | B30: ='T12 Actuals'!$B$23 -> 523415 | C30: =IFERROR(B30/Units/12,0) -> 454.3533 | D30: =D15-D29 -> 484834.88 | E30: =E15-E29 -> 694246.48 | F30: =F15-F29 -> 727300.76 | G30: =G15-G29 -> 749119.78 | H30: =H15-H29 -> 771593.37 | I30: =I15-I29 -> 794741.17 | J30: =J15-J29 -> 818583.4 | K30: =K15-K29 -> 843140.9 | N30: =IFERROR($E30/Inputs!$B$13,"") -> 7231.7342 | O30: =IFERROR($E30/$E$15,"") -> 0.47128708
A31: NOI Margin | B31: =IFERROR(B30/B15,0) -> 0.42519496 | D31: =IFERROR(D30/D15,0) -> 0.39050496 | E31: =IFERROR(E30/E15,0) -> 0.47128708 | F31: =IFERROR(F30/F15,0) -> 0.47531364 | G31: =IFERROR(G30/G15,0) -> 0.47531364 | H31: =IFERROR(H30/H15,0) -> 0.47531363 | I31: =IFERROR(I30/I15,0) -> 0.47531363 | J31: =IFERROR(J30/J15,0) -> 0.47531363 | K31: =IFERROR(K30/K15,0) -> 0.47531363
A33: FINANCING & CASH FLOW
A34: Annual Mortgage Payment (Debt Service) | D34: ='Debt & Exit'!$B$17 -> 325023.83 | E34: ='Debt & Exit'!$B$17 -> 325023.83 | F34: ='Debt & Exit'!$B$17 -> 325023.83 | G34: ='Debt & Exit'!$B$17 -> 325023.83 | H34: ='Debt & Exit'!$B$17 -> 325023.83 | I34: ='Debt & Exit'!$B$17 -> 325023.83 | J34: ='Debt & Exit'!$B$17 -> 325023.83 | K34: ='Debt & Exit'!$B$17 -> 325023.83
A35: Net Income After Debt Service | D35: =D30-D34 -> 159811.05 | E35: =E30-E34 -> 369222.65 | F35: =F30-F34 -> 402276.92 | G35: =G30-G34 -> 424095.95 | H35: =H30-H34 -> 446569.54 | I35: =I30-I34 -> 469717.34 | J35: =J30-J34 -> 493559.57 | K35: =K30-K34 -> 518117.07
A36: Cash-on-Cash Return % | D36: =D35/'Debt & Exit'!$B$12 -> 0.043550959 | E36: =E35/'Debt & Exit'!$B$12 -> 0.10061883 | F36: =F35/'Debt & Exit'!$B$12 -> 0.10962662 | G36: =G35/'Debt & Exit'!$B$12 -> 0.11557264 | H36: =H35/'Debt & Exit'!$B$12 -> 0.12169704 | I36: =I35/'Debt & Exit'!$B$12 -> 0.12800517 | J36: =J35/'Debt & Exit'!$B$12 -> 0.13450254 | K36: =K35/'Debt & Exit'!$B$12 -> 0.14119484
A37: Replacement Reserves (below the line) | D37: =Inputs!$B$54*Units -> 24000 | E37: =D37*(1+Inputs!$B$22) -> 24720 | F37: =E37*(1+Inputs!$B$22) -> 25461.6 | G37: =F37*(1+Inputs!$B$22) -> 26225.448 | H37: =G37*(1+Inputs!$B$22) -> 27012.211 | I37: =H37*(1+Inputs!$B$22) -> 27822.578 | J37: =I37*(1+Inputs!$B$22) -> 28657.255 | K37: =J37*(1+Inputs!$B$22) -> 29516.973
A38: Net Cash Flow After Reserves | D38: =D35-D37 -> 135811.05 | E38: =E35-E37 -> 344502.65 | F38: =F35-F37 -> 376815.32 | G38: =G35-G37 -> 397870.5 | H38: =H35-H37 -> 419557.33 | I38: =I35-I37 -> 441894.76 | J38: =J35-J37 -> 464902.32 | K38: =K35-K37 -> 488600.1
A39: Cash-on-Cash After Reserves % | D39: =D38/'Debt & Exit'!$B$12 -> 0.037010591 | E39: =E38/'Debt & Exit'!$B$12 -> 0.093882247 | F39: =F38/'Debt & Exit'!$B$12 -> 0.10268795 | G39: =G38/'Debt & Exit'!$B$12 -> 0.1084258 | H39: =H38/'Debt & Exit'!$B$12 -> 0.1143358 | I39: =I38/'Debt & Exit'!$B$12 -> 0.12042309 | J39: =J38/'Debt & Exit'!$B$12 -> 0.126693 | K39: =K38/'Debt & Exit'!$B$12 -> 0.13315101
A41: Reserves sit below NOI on purpose. NOI is what the purchase cap rate, the exit cap rate and every scenario value are applied to, so charging reserves into operating expenses would quietly change the price of the deal. The lines above show what the reserve costs in cash without touching that.

Sheet Debt & Exit
A1: Debt, Exit, and Returns
A2: =B6 -> 8442177.4 | B2: =B8 -> 5909524.2 | C2: =B25 -> 0.19043256 | D2: =B26 -> 2.2099212
A3: PURCHASE PRICE | B3: LOAN AMOUNT | C3: ="LEVERED IRR ("&Inputs!$B$17&"-YR)" -> LEVERED IRR (5-YR) | D3: EQUITY MULTIPLE
A5: Metric | B5: Amount | C5: Notes
A6: Purchase Price | B6: =IF(Inputs!$B$6>0,Inputs!$B$6,'T12 Actuals'!$B$23/Inputs!$B$14) -> 8442177.4 | C6: T12 NOI / purchase cap, unless a manual override price is entered on Inputs (B30). price from actual T12 NOI.
A7: Price Per Unit | B7: =IFERROR(B6/Inputs!$B$13,0) -> 87939.348 | C7: Purchase price / units. Market pricing check.
A8: Loan Amount | B8: =B6*Inputs!$B$15 -> 5909524.2 | C8: Purchase price x 70% LTV. Debt sizing.
A9: Equity Before Capex | B9: =B6-B8 -> 2532653.2 | C9: Purchase price - loan amount. Base equity need.
A10: Total Capex | B10: =Inputs!$B$36 -> 883600 | C10: Linked to Inputs total capex. Renovation/common budget.
A11: Upfront Acquisition Closing Cost | B11: =B6*Inputs!$B$20 -> 253265.32 | C11: Purchase price x 3%. Upfront acquisition closing cost.
A12: Initial Equity Required | B12: =B6+B10+B11-B8 -> 3669518.5 | C12: Purchase price + capex + upfront closing cost - loan. Used as Year 0 cash outflow.
A13: Gross Exit Value | B13: =INDEX('Pro Forma'!$D$30:$K$30,Inputs!$B$17)/Inputs!$B$18 -> 12859889 | C13: The hold-period year's NOI / exit cap rate. Change Hold Period on Inputs and the sale moves with it. Sale proceeds before costs.
A14: Disposition Cost at Exit | B14: =B13*Inputs!$B$19 -> 642994.47 | C14: Gross exit value x 5%. Closing cost subtracted at exit.
A15: Loan Payoff | B15: =$B$18 -> 5909524.2 | C15: Loan balance at the end of the hold period; equals the original loan when interest-only.
A16: Net Sale Proceeds | B16: =B13-B14-B15 -> 6307370.8 | C16: Gross exit value - disposition cost - loan payoff. Cash received at sale before final year cash flow.
A17: Annual Debt Service (computed) | B17: =IF(Inputs!$B$46=0,$B$8*Inputs!$B$16,-PMT(Inputs!$B$16,Inputs!$B$46,$B$8)) -> 325023.83 | C17: FIX #6: interest-only if amortization=0, else amortizing payment.
A18: =CONCATENATE("Acq Loan Balance @ Exit (Yr ",Inputs!$B$17,")") -> Acq Loan Balance @ Exit (Yr 5) | B18: =$B$8*(1+Inputs!$B$16)^Inputs!$B$17-$B$17*((1+Inputs!$B$16)^Inputs!$B$17-1)/Inputs!$B$16 -> 5909524.2 | C18: Remaining principal at sale; equals full loan when interest-only.
A19: Metric | B19: Year 0 | C19: Year 1 | D19: Year 2 | E19: Year 3 | F19: Year 4 | G19: Year 5 | H19: Year 6 | I19: Year 7 | J19: Year 8 | K19: How/Why
A20: NOI | C20: ='Pro Forma'!$D$30 -> 484834.88 | D20: ='Pro Forma'!$E$30 -> 694246.48 | E20: ='Pro Forma'!$F$30 -> 727300.76 | F20: ='Pro Forma'!$G$30 -> 749119.78 | G20: ='Pro Forma'!$H$30 -> 771593.37 | H20: ='Pro Forma'!$I$30 -> 794741.17 | I20: ='Pro Forma'!$J$30 -> 818583.4 | J20: ='Pro Forma'!$K$30 -> 843140.9 | K20: Linked from the Pro Forma, Years 1-8.
A21: Debt Service | C21: =IF(Inputs!$B$17>=1,$B$17,0) -> 325023.83 | D21: =IF(Inputs!$B$17>=2,$B$17,0) -> 325023.83 | E21: =IF(Inputs!$B$17>=3,$B$17,0) -> 325023.83 | F21: =IF(Inputs!$B$17>=4,$B$17,0) -> 325023.83 | G21: =IF(Inputs!$B$17>=5,$B$17,0) -> 325023.83 | H21: =IF(Inputs!$B$17>=6,$B$17,0) -> 0 | I21: =IF(Inputs!$B$17>=7,$B$17,0) -> 0 | J21: =IF(Inputs!$B$17>=8,$B$17,0) -> 0 | K21: Acquisition debt service; zero once the hold period is over.
A22: Cash Flow After Debt | C22: =IF(Inputs!$B$17>=1,C20-C21,0) -> 159811.05 | D22: =IF(Inputs!$B$17>=2,D20-D21,0) -> 369222.65 | E22: =IF(Inputs!$B$17>=3,E20-E21,0) -> 402276.92 | F22: =IF(Inputs!$B$17>=4,F20-F21,0) -> 424095.95 | G22: =IF(Inputs!$B$17>=5,G20-G21,0) -> 446569.54 | H22: =IF(Inputs!$B$17>=6,H20-H21,0) -> 0 | I22: =IF(Inputs!$B$17>=7,I20-I21,0) -> 0 | J22: =IF(Inputs!$B$17>=8,J20-J21,0) -> 0 | K22: NOI less debt service, through the hold period only.
A23: Sale Proceeds | C23: =IF(Inputs!$B$17=1,$B$16,0) -> 0 | D23: =IF(Inputs!$B$17=2,$B$16,0) -> 0 | E23: =IF(Inputs!$B$17=3,$B$16,0) -> 0 | F23: =IF(Inputs!$B$17=4,$B$16,0) -> 0 | G23: =IF(Inputs!$B$17=5,$B$16,0) -> 6307370.8 | H23: =IF(Inputs!$B$17=6,$B$16,0) -> 0 | I23: =IF(Inputs!$B$17=7,$B$16,0) -> 0 | J23: =IF(Inputs!$B$17=8,$B$16,0) -> 0 | K23: Net sale proceeds, in whichever year the Inputs hold period says.
A24: Total Cash Flow | B24: =-$B$12 -> -3669518.5 | C24: =C22+C23 -> 159811.05 | D24: =D22+D23 -> 369222.65 | E24: =E22+E23 -> 402276.92 | F24: =F22+F23 -> 424095.95 | G24: =G22+G23 -> 6753940.4 | H24: =H22+H23 -> 0 | I24: =I22+I23 -> 0 | J24: =J22+J23 -> 0 | K24: Year 0 is initial equity; operating cash flow plus net sale proceeds in the exit year.
A25: Levered IRR | B25: =IFERROR(IRR(B24:J24),0) -> 0.19043256 | K25: IRR of Year 0 through Year 8 total cash flows, including sale proceeds.
A26: Equity Multiple | B26: =SUM(C24:J24)/ABS(B24) -> 2.2099212 | K26: Total positive cash distributions / initial equity.
A27: Annual Cash-on-Cash | C27: =C22/$B$12 -> 0.043550959 | D27: =D22/$B$12 -> 0.10061883 | E27: =E22/$B$12 -> 0.10962662 | F27: =F22/$B$12 -> 0.11557264 | G27: =G22/$B$12 -> 0.12169704 | H27: =H22/$B$12 -> 0 | I27: =I22/$B$12 -> 0 | J27: =J22/$B$12 -> 0 | K27: Annual cash flow after debt / initial equity. Shows distribution timing.
A28: Average Cash-on-Cash | B28: =IFERROR(SUM(C27:J27)/Inputs!$B$17,0) -> 0.098213217 | K28: Average annual CoC across the hold period.

Sheet Exit Scenarios
A1: Exit Scenarios - Sale and Refinance Options Through Year 8
A2: =IFERROR(INDEX(B5:G5,MATCH(MAX(B14:G14),B14:G14,0)),0) -> Sale Year 3 | B2: =MAX(B14:G14) -> 0.22213197 | C2: =C16 -> 0.10061883 | D2: =Inputs!$B$47 -> 0.16
A3: BEST IRR SCENARIO | B3: BEST IRR | C3: YEAR 2 CASH-ON-CASH | D3: IRR TARGET
A5: Metric | B5: Sale Year 3 | C5: Sale Year 5 | D5: Sale Year 8 | E5: Refi Yr3 + Sale Yr5 | F5: Refi Yr3 + Sale Yr8 | G5: Refi Yr5 + Sale Yr8 | H5: Notes
A6: Exit / Refi Cap Rate | B6: =Inputs!$B$18 -> 0.06 | C6: =Inputs!$B$18 -> 0.06 | D6: =Inputs!$B$18 -> 0.06 | E6: =TEXT(Inputs!$B$40,"0.0%") & " refi / " & TEXT(Inputs!$B$18,"0.0%") & " exit" -> 5.9% refi / 6.0% exit | F6: =TEXT(Inputs!$B$40,"0.0%") & " refi / " & TEXT(Inputs!$B$18,"0.0%") & " exit" -> 5.9% refi / 6.0% exit | G6: =TEXT(Inputs!$B$40,"0.0%") & " refi / " & TEXT(Inputs!$B$18,"0.0%") & " exit" -> 5.9% refi / 6.0% exit | H6: Refi cases size the new loan on the refi cap in the refi year, then sell on the exit cap.
A7: Hold Period (yrs) | B7: 3 | C7: 5 | D7: 8 | E7: 5 | F7: 8 | G7: 8 | H7: Sale year for the scenario. Year 6-8 NOI is real Pro Forma NOI, not a stand-in.
A8: Gross Sale Value | B8: ='Pro Forma'!$F$30/Inputs!$B$18 -> 12121679 | C8: ='Pro Forma'!$H$30/Inputs!$B$18 -> 12859889 | D8: ='Pro Forma'!$K$30/Inputs!$B$18 -> 14052348 | E8: ='Pro Forma'!$H$30/Inputs!$B$18 -> 12859889 | F8: ='Pro Forma'!$K$30/Inputs!$B$18 -> 14052348 | G8: ='Pro Forma'!$K$30/Inputs!$B$18 -> 14052348 | H8: That year's Pro Forma NOI / exit cap rate.
A9: Net Refi Proceeds | E9: =$B$33-$B$30-$B$33*Inputs!$B$42 -> 2561390.5 | F9: =$B$33-$B$30-$B$33*Inputs!$B$42 -> 2561390.5 | G9: =$B$37-$B$31-$B$37*Inputs!$B$42 -> 3077269.2 | H9: Cash-out at refi: new loan less the acquisition balance and refi closing cost. Treated as an investor distribution, not added spend.
A10: Disposition Cost (at sale) | B10: =B8*Inputs!$B$19 -> 606083.96 | C10: =C8*Inputs!$B$19 -> 642994.47 | D10: =D8*Inputs!$B$19 -> 702617.42 | E10: =E8*Inputs!$B$19 -> 642994.47 | F10: =F8*Inputs!$B$19 -> 702617.42 | G10: =G8*Inputs!$B$19 -> 702617.42 | H10: Disposition / closing cost % of sale value.
A11: Loan Payoff at Sale | B11: =$B$30 -> 5909524.2 | C11: =$B$31 -> 5909524.2 | D11: =$B$32 -> 5909524.2 | E11: =$B$35 -> 8556479.5 | F11: =$B$36 -> 8556479.5 | G11: =$B$39 -> 9077569 | H11: Refi cases repay the new refi loan at sale; the others repay the acquisition loan.
A12: Net Sale Proceeds | B12: =B8-B10-B11 -> 5606071.1 | C12: =C8-C10-C11 -> 6307370.8 | D12: =D8-D10-D11 -> 7440206.8 | E12: =E8-E10-E11 -> 3660415.5 | F12: =F8-F10-F11 -> 4793251.5 | G12: =G8-G10-G11 -> 4272161.9 | H12: Sale value - disposition cost - loan payoff.
A13: Initial Equity | B13: ='Debt & Exit'!$B$12 -> 3669518.5 | C13: ='Debt & Exit'!$B$12 -> 3669518.5 | D13: ='Debt & Exit'!$B$12 -> 3669518.5 | E13: ='Debt & Exit'!$B$12 -> 3669518.5 | F13: ='Debt & Exit'!$B$12 -> 3669518.5 | G13: ='Debt & Exit'!$B$12 -> 3669518.5 | H13: Same day-one equity across scenarios.
A14: Levered IRR | B14: =IFERROR(IRR(B21:E21),"NM") -> 0.22213197 | C14: =IFERROR(IRR(B22:G22),"NM") -> 0.19043256 | D14: =IFERROR(IRR(B23:J23),"NM") -> 0.17158252 | E14: =IFERROR(IRR(B24:G24),"NM") -> 0.21428408 | F14: =IFERROR(IRR(B25:J25),"NM") -> 0.20717234 | G14: =IFERROR(IRR(B26:J26),"NM") -> 0.19016913 | H14: IRR includes interim distributions, refi proceeds, and final net sale proceeds.
A15: Equity Multiple | B15: =SUM(C21:E21)/'Debt & Exit'!$B$12 -> 1.7815366 | C15: =SUM(C22:G22)/'Debt & Exit'!$B$12 -> 2.2099212 | D15: =SUM(C23:J23)/'Debt & Exit'!$B$12 -> 2.9223389 | E15: =SUM(C24:G24)/'Debt & Exit'!$B$12 -> 2.1095883 | F15: =SUM(C25:J25)/'Debt & Exit'!$B$12 -> 2.7064833 | G15: =SUM(C26:J26)/'Debt & Exit'!$B$12 -> 2.7588606 | H15: Total distributions / equity in.
A16: Year 2 Cash-on-Cash | B16: =$D$21/'Debt & Exit'!$B$12 -> 0.10061883 | C16: =$D$21/'Debt & Exit'!$B$12 -> 0.10061883 | D16: =$D$21/'Debt & Exit'!$B$12 -> 0.10061883 | E16: =$D$21/'Debt & Exit'!$B$12 -> 0.10061883 | F16: =$D$21/'Debt & Exit'!$B$12 -> 0.10061883 | G16: =$D$21/'Debt & Exit'!$B$12 -> 0.10061883 | H16: Year 2 operating cash flow / equity - identical pre-refi across scenarios.
A17: Avg Cash-on-Cash | B17: =AVERAGE($B$42:$D$42)/'Debt & Exit'!$B$12 -> 0.084598802 | C17: =AVERAGE($B$42:$F$42)/'Debt & Exit'!$B$12 -> 0.098213217 | D17: =AVERAGE($B$42:$I$42)/'Debt & Exit'!$B$12 -> 0.11184608 | E17: =AVERAGE($B$42:$D$42,$E$43:$F$43)/'Debt & Exit'!$B$12 -> 0.082810183 | F17: =AVERAGE($B$42:$D$42,$E$43:$I$43)/'Debt & Exit'!$B$12 -> 0.087778838 | G17: =AVERAGE($B$42:$F$42,$G$44:$I$44)/'Debt & Exit'!$B$12 -> 0.094503509 | H17: Average operating CoC over the scenario's hold, on whichever debt is in place.
A18: Refi Case Interpretation | B18: No refinance | C18: No refinance | D18: No refinance | E18: Cash-out refinance in Year 3; sell Year 5 | F18: Cash-out refinance in Year 3; sell Year 8 | G18: Cash-out refinance in Year 5; sell Year 8 | H18: No incremental upgrades are modeled from refi proceeds unless a separate use-of-proceeds budget and NOI ramp are added.
A19: Gross Sale Value / Unit (max price per door) | B19: =IFERROR(B8/Inputs!$B$13,"n/a") -> 126267.49 | C19: =IFERROR(C8/Inputs!$B$13,"n/a") -> 133957.18 | D19: =IFERROR(D8/Inputs!$B$13,"n/a") -> 146378.63 | E19: =IFERROR(E8/Inputs!$B$13,"n/a") -> 133957.18 | F19: =IFERROR(F8/Inputs!$B$13,"n/a") -> 146378.63 | G19: =IFERROR(G8/Inputs!$B$13,"n/a") -> 146378.63 | H19: Gross sale value / unit count (Inputs). What the exit asks a buyer to pay per door - the ceiling the local market will actually clear, regardless of what the cap rate math says.
A20: Equity Cash Flow | B20: Year 0 | C20: Year 1 | D20: Year 2 | E20: Year 3 | F20: Year 4 | G20: Year 5 | H20: Year 6 | I20: Year 7 | J20: Year 8
A21: Sale Year 3 | B21: =-'Debt & Exit'!$B$12 -> -3669518.5 | C21: =$B$42 -> 159811.05 | D21: =$C$42 -> 369222.65 | E21: =$D$42+$B$12 -> 6008348
A22: Sale Year 5 | B22: =-'Debt & Exit'!$B$12 -> -3669518.5 | C22: =$B$42 -> 159811.05 | D22: =$C$42 -> 369222.65 | E22: =$D$42 -> 402276.92 | F22: =$E$42 -> 424095.95 | G22: =$F$42+$C$12 -> 6753940.4
A23: Sale Year 8 | B23: =-'Debt & Exit'!$B$12 -> -3669518.5 | C23: =$B$42 -> 159811.05 | D23: =$C$42 -> 369222.65 | E23: =$D$42 -> 402276.92 | F23: =$E$42 -> 424095.95 | G23: =$F$42 -> 446569.54 | H23: =$G$42 -> 469717.34 | I23: =$H$42 -> 493559.57 | J23: =$I$42+$D$12 -> 7958323.9
A24: Refi Yr3 + Sale Yr5 | B24: =-'Debt & Exit'!$B$12 -> -3669518.5 | C24: =$B$42 -> 159811.05 | D24: =$C$42 -> 369222.65 | E24: =$D$42+$E$9 -> 2963667.4 | F24: =$E$43 -> 282791.65 | G24: =$F$43+$E$12 -> 3965680.8
A25: Refi Yr3 + Sale Yr8 | B25: =-'Debt & Exit'!$B$12 -> -3669518.5 | C25: =$B$42 -> 159811.05 | D25: =$C$42 -> 369222.65 | E25: =$D$42+$F$9 -> 2963667.4 | F25: =$E$43 -> 282791.65 | G25: =$F$43 -> 305265.24 | H25: =$G$43 -> 328413.04 | I25: =$H$43 -> 352255.27 | J25: =$I$43+$F$12 -> 5170064.3
A26: Refi Yr5 + Sale Yr8 | B26: =-'Debt & Exit'!$B$12 -> -3669518.5 | C26: =$B$42 -> 159811.05 | D26: =$C$42 -> 369222.65 | E26: =$D$42 -> 402276.92 | F26: =$E$42 -> 424095.95 | G26: =$F$42+$G$9 -> 3523838.7 | H26: =$G$44 -> 300013.66 | I26: =$H$44 -> 323855.89 | J26: =$I$44+$G$12 -> 4620575.3
A28: Supporting Calcs | H28: How calculated
A29: Annual acquisition debt service | B29: ='Debt & Exit'!$B$17 -> 325023.83 | H29: Linked from Debt & Exit.
A30: Acq loan balance @ Yr3 | B30: =IF(Inputs!$B$16=0,'Debt & Exit'!$B$8-$B$29*3,'Debt & Exit'!$B$8*(1+Inputs!$B$16)^3-$B$29*((1+Inputs!$B$16)^3-1)/Inputs!$B$16) -> 5909524.2 | H30: Acquisition loan balance after 3 years of debt service.
A31: Acq loan balance @ Yr5 | B31: =IF(Inputs!$B$16=0,'Debt & Exit'!$B$8-$B$29*5,'Debt & Exit'!$B$8*(1+Inputs!$B$16)^5-$B$29*((1+Inputs!$B$16)^5-1)/Inputs!$B$16) -> 5909524.2 | H31: Acquisition loan balance after 5 years of debt service.
A32: Acq loan balance @ Yr8 | B32: =IF(Inputs!$B$16=0,'Debt & Exit'!$B$8-$B$29*8,'Debt & Exit'!$B$8*(1+Inputs!$B$16)^8-$B$29*((1+Inputs!$B$16)^8-1)/Inputs!$B$16) -> 5909524.2 | H32: Acquisition loan balance after 8 years of debt service.
A33: Refi @ Yr3 - new loan | B33: =('Pro Forma'!$F$30/Inputs!$B$40)*Inputs!$B$41 -> 8556479.5 | H33: Year 3 NOI / refi cap rate x refi LTV.
A34: Refi @ Yr3 - annual debt service | B34: =IF(Inputs!$B$46=0,$B$33*Inputs!$B$43,-PMT(Inputs!$B$43,Inputs!$B$46,$B$33)) -> 466328.13 | H34: Interest-only unless an amortization term is set on Inputs.
A35: Refi @ Yr3 - balance @ Yr5 | B35: =IF(Inputs!$B$43=0,$B$33-$B$34*2,$B$33*(1+Inputs!$B$43)^2-$B$34*((1+Inputs!$B$43)^2-1)/Inputs!$B$43) -> 8556479.5 | H35: New refi loan payoff if sold in Year 5.
A36: Refi @ Yr3 - balance @ Yr8 | B36: =IF(Inputs!$B$43=0,$B$33-$B$34*5,$B$33*(1+Inputs!$B$43)^5-$B$34*((1+Inputs!$B$43)^5-1)/Inputs!$B$43) -> 8556479.5 | H36: New refi loan payoff if sold in Year 8.
A37: Refi @ Yr5 - new loan | B37: =('Pro Forma'!$H$30/Inputs!$B$40)*Inputs!$B$41 -> 9077569 | H37: Year 5 NOI / refi cap rate x refi LTV.
A38: Refi @ Yr5 - annual debt service | B38: =IF(Inputs!$B$46=0,$B$37*Inputs!$B$43,-PMT(Inputs!$B$43,Inputs!$B$46,$B$37)) -> 494727.51 | H38: Interest-only unless an amortization term is set on Inputs.
A39: Refi @ Yr5 - balance @ Yr8 | B39: =IF(Inputs!$B$43=0,$B$37-$B$38*3,$B$37*(1+Inputs!$B$43)^3-$B$38*((1+Inputs!$B$43)^3-1)/Inputs!$B$43) -> 9077569 | H39: New refi loan payoff if sold in Year 8.
A40: Operating Cash Flow by Year (Pro Forma NOI less debt service) | H40: Every scenario's cash flow is built from these rows, so the grid stays independent of the Inputs hold period on Debt & Exit.
B41: Year 1 | C41: Year 2 | D41: Year 3 | E41: Year 4 | F41: Year 5 | G41: Year 6 | H41: Year 7 | I41: Year 8
A42: On acquisition debt | B42: ='Pro Forma'!$D$30-$B$29 -> 159811.05 | C42: ='Pro Forma'!$E$30-$B$29 -> 369222.65 | D42: ='Pro Forma'!$F$30-$B$29 -> 402276.92 | E42: ='Pro Forma'!$G$30-$B$29 -> 424095.95 | F42: ='Pro Forma'!$H$30-$B$29 -> 446569.54 | G42: ='Pro Forma'!$I$30-$B$29 -> 469717.34 | H42: ='Pro Forma'!$J$30-$B$29 -> 493559.57 | I42: ='Pro Forma'!$K$30-$B$29 -> 518117.07
A43: On Yr3 refi debt | E43: ='Pro Forma'!$G$30-$B$34 -> 282791.65 | F43: ='Pro Forma'!$H$30-$B$34 -> 305265.24 | G43: ='Pro Forma'!$I$30-$B$34 -> 328413.04 | H43: ='Pro Forma'!$J$30-$B$34 -> 352255.27 | I43: ='Pro Forma'!$K$30-$B$34 -> 376812.77
A44: On Yr5 refi debt | G44: ='Pro Forma'!$I$30-$B$38 -> 300013.66 | H44: ='Pro Forma'!$J$30-$B$38 -> 323855.89 | I44: ='Pro Forma'!$K$30-$B$38 -> 348413.39
A46: DECISION SUMMARY - DOES EACH EXIT CLEAR OUR TARGETS?
A47: Scenario | B47: IRR | C47: vs IRR Target | D47: Yr2 CoC | E47: vs CoC Target
A48: Sale Year 3 | B48: =B14 -> 0.22213197 | C48: =IF(AND(ISNUMBER(B14),B14>=Inputs!$B$47),"PASS","FLAG") -> PASS | D48: =B16 -> 0.10061883 | E48: =IF(B16>=Inputs!$B$48,"PASS","FLAG") -> PASS
A49: Sale Year 5 | B49: =C14 -> 0.19043256 | C49: =IF(AND(ISNUMBER(C14),C14>=Inputs!$B$47),"PASS","FLAG") -> PASS | D49: =C16 -> 0.10061883 | E49: =IF(C16>=Inputs!$B$48,"PASS","FLAG") -> PASS
A50: Sale Year 8 | B50: =D14 -> 0.17158252 | C50: =IF(AND(ISNUMBER(D14),D14>=Inputs!$B$47),"PASS","FLAG") -> PASS | D50: =D16 -> 0.10061883 | E50: =IF(D16>=Inputs!$B$48,"PASS","FLAG") -> PASS
A51: Refi Yr3 + Sale Yr5 | B51: =E14 -> 0.21428408 | C51: =IF(AND(ISNUMBER(E14),E14>=Inputs!$B$47),"PASS","FLAG") -> PASS | D51: =E16 -> 0.10061883 | E51: =IF(E16>=Inputs!$B$48,"PASS","FLAG") -> PASS
A52: Refi Yr3 + Sale Yr8 | B52: =F14 -> 0.20717234 | C52: =IF(AND(ISNUMBER(F14),F14>=Inputs!$B$47),"PASS","FLAG") -> PASS | D52: =F16 -> 0.10061883 | E52: =IF(F16>=Inputs!$B$48,"PASS","FLAG") -> PASS
A53: Refi Yr5 + Sale Yr8 | B53: =G14 -> 0.19016913 | C53: =IF(AND(ISNUMBER(G14),G14>=Inputs!$B$47),"PASS","FLAG") -> PASS | D53: =G16 -> 0.10061883 | E53: =IF(G16>=Inputs!$B$48,"PASS","FLAG") -> PASS
A55: How to read this | B55: IRR is an ANNUALISED return, so a later sale can earn more total profit at a lower IRR. Where the renovation programme finishes before the hold ends, NOI flattens to inflation and every extra year dilutes the IRR - which is why an early sale, or a refinance that pulls cash out at the top of the lift and keeps the asset, usually scores best. Read IRR and Equity Multiple together, never alone.

Sheet Max Price Solver
A1: Max Price Solver - What Purchase Price Makes This Deal Work? (sale in the Inputs hold-period year)
A2: =B42 -> 8912387.4 | B2: =B43 -> 92837.369 | C2: =B44 -> -0.055697712 | D2: ='Debt & Exit'!$B$6 -> 8442177.4
A3: MAX PRICE @ 16% IRR | B3: MAX PRICE / UNIT | C3: DISCOUNT vs ASK | D3: CURRENT ASK
A4: Each column reprices the whole deal at a different purchase cap rate: price, loan, equity, debt service, and property tax. If county tax inputs are missing, taxes fall back to actual T12 property tax grown forward. All other assumptions come from the Inputs tab.
A6: Metric | B6: Cap 3.00% | C6: Cap 3.50% | D6: Cap 4.00% | E6: Cap 4.50% | F6: Cap 5.00% | G6: Cap 5.50% | H6: Cap 6.00% | I6: Cap 6.50% | J6: Cap 7.00% | K6: Cap 7.50% | L6: Cap 8.00% | M6: Cap 8.50% | N6: Cap 9.00% | O6: Cap 9.50% | P6: Cap 10.00% | Q6: Cap 10.50% | R6: Cap 11.00% | S6: Cap 11.50% | T6: Cap 12.00%
A7: Candidate Purchase Cap Rate | B7: 0.03 | C7: 0.035 | D7: 0.04 | E7: 0.045 | F7: 0.05 | G7: 0.055 | H7: 0.06 | I7: 0.065 | J7: 0.07 | K7: 0.075 | L7: 0.08 | M7: 0.085 | N7: 0.09 | O7: 0.095 | P7: 0.1 | Q7: 0.105 | R7: 0.11 | S7: 0.115 | T7: 0.12
A8: Implied Purchase Price | B8: ='T12 Actuals'!$B$23/B7 -> 17447167 | C8: ='T12 Actuals'!$B$23/C7 -> 14954714 | D8: ='T12 Actuals'!$B$23/D7 -> 13085375 | E8: ='T12 Actuals'!$B$23/E7 -> 11631444 | F8: ='T12 Actuals'!$B$23/F7 -> 10468300 | G8: ='T12 Actuals'!$B$23/G7 -> 9516636.4 | H8: ='T12 Actuals'!$B$23/H7 -> 8723583.3 | I8: ='T12 Actuals'!$B$23/I7 -> 8052538.5 | ... T8: ='T12 Actuals'!$B$23/T7 -> 4361791.7
A9: Price Per Unit | B9: =IFERROR(B8/Inputs!$B$13,0) -> 181741.32 | C9: =IFERROR(C8/Inputs!$B$13,0) -> 155778.27 | D9: =IFERROR(D8/Inputs!$B$13,0) -> 136305.99 | E9: =IFERROR(E8/Inputs!$B$13,0) -> 121160.88 | F9: =IFERROR(F8/Inputs!$B$13,0) -> 109044.79 | G9: =IFERROR(G8/Inputs!$B$13,0) -> 99131.629 | H9: =IFERROR(H8/Inputs!$B$13,0) -> 90870.66 | I9: =IFERROR(I8/Inputs!$B$13,0) -> 83880.609 | ... T9: =IFERROR(T8/Inputs!$B$13,0) -> 45435.33
A10: Loan Amount (70% LTV) | B10: =B8*Inputs!$B$15 -> 12213017 | C10: =C8*Inputs!$B$15 -> 10468300 | D10: =D8*Inputs!$B$15 -> 9159762.5 | E10: =E8*Inputs!$B$15 -> 8142011.1 | F10: =F8*Inputs!$B$15 -> 7327810 | G10: =G8*Inputs!$B$15 -> 6661645.5 | H10: =H8*Inputs!$B$15 -> 6106508.3 | I10: =I8*Inputs!$B$15 -> 5636776.9 | ... T10: =T8*Inputs!$B$15 -> 3053254.2
A11: Initial Equity (price + capex + 3% closing - loan) | B11: =B8+Inputs!$B$36+B8*Inputs!$B$20-B10 -> 6641165 | C11: =C8+Inputs!$B$36+C8*Inputs!$B$20-C10 -> 5818655.7 | D11: =D8+Inputs!$B$36+D8*Inputs!$B$20-D10 -> 5201773.8 | E11: =E8+Inputs!$B$36+E8*Inputs!$B$20-E10 -> 4721976.7 | F11: =F8+Inputs!$B$36+F8*Inputs!$B$20-F10 -> 4338139 | G11: =G8+Inputs!$B$36+G8*Inputs!$B$20-G10 -> 4024090 | H11: =H8+Inputs!$B$36+H8*Inputs!$B$20-H10 -> 3762382.5 | I11: =I8+Inputs!$B$36+I8*Inputs!$B$20-I10 -> 3540937.7 | ... T11: =T8+Inputs!$B$36+T8*Inputs!$B$20-T10 -> 2322991.3
A12: Annual Debt Service | B12: =IF(Inputs!$B$46=0,B10*Inputs!$B$16,-PMT(Inputs!$B$16,Inputs!$B$46,B10)) -> 671715.92 | C12: =IF(Inputs!$B$46=0,C10*Inputs!$B$16,-PMT(Inputs!$B$16,Inputs!$B$46,C10)) -> 575756.5 | D12: =IF(Inputs!$B$46=0,D10*Inputs!$B$16,-PMT(Inputs!$B$16,Inputs!$B$46,D10)) -> 503786.94 | E12: =IF(Inputs!$B$46=0,E10*Inputs!$B$16,-PMT(Inputs!$B$16,Inputs!$B$46,E10)) -> 447810.61 | F12: =IF(Inputs!$B$46=0,F10*Inputs!$B$16,-PMT(Inputs!$B$16,Inputs!$B$46,F10)) -> 403029.55 | G12: =IF(Inputs!$B$46=0,G10*Inputs!$B$16,-PMT(Inputs!$B$16,Inputs!$B$46,G10)) -> 366390.5 | H12: =IF(Inputs!$B$46=0,H10*Inputs!$B$16,-PMT(Inputs!$B$16,Inputs!$B$46,H10)) -> 335857.96 | I12: =IF(Inputs!$B$46=0,I10*Inputs!$B$16,-PMT(Inputs!$B$16,Inputs!$B$46,I10)) -> 310022.73 | ... T12: =IF(Inputs!$B$46=0,T10*Inputs!$B$16,-PMT(Inputs!$B$16,Inputs!$B$46,T10)) -> 167928.98
A13: Year 1 Property Tax (per reassessment policy) | B13: =IF(OR(Tax!$B$8<=0,Tax!$B$9<=0),Tax!$B$13,(Tax!$B$8+(B8-Tax!$B$8)*Tax!$B$19)*Tax!$B$9/1000+Tax!$B$10) -> 291800.79 | C13: =IF(OR(Tax!$B$8<=0,Tax!$B$9<=0),Tax!$B$13,(Tax!$B$8+(C8-Tax!$B$8)*Tax!$B$19)*Tax!$B$9/1000+Tax!$B$10) -> 261928.75 | D13: =IF(OR(Tax!$B$8<=0,Tax!$B$9<=0),Tax!$B$13,(Tax!$B$8+(D8-Tax!$B$8)*Tax!$B$19)*Tax!$B$9/1000+Tax!$B$10) -> 239524.72 | E13: =IF(OR(Tax!$B$8<=0,Tax!$B$9<=0),Tax!$B$13,(Tax!$B$8+(E8-Tax!$B$8)*Tax!$B$19)*Tax!$B$9/1000+Tax!$B$10) -> 222099.36 | F13: =IF(OR(Tax!$B$8<=0,Tax!$B$9<=0),Tax!$B$13,(Tax!$B$8+(F8-Tax!$B$8)*Tax!$B$19)*Tax!$B$9/1000+Tax!$B$10) -> 208159.08 | G13: =IF(OR(Tax!$B$8<=0,Tax!$B$9<=0),Tax!$B$13,(Tax!$B$8+(G8-Tax!$B$8)*Tax!$B$19)*Tax!$B$9/1000+Tax!$B$10) -> 196753.39 | H13: =IF(OR(Tax!$B$8<=0,Tax!$B$9<=0),Tax!$B$13,(Tax!$B$8+(H8-Tax!$B$8)*Tax!$B$19)*Tax!$B$9/1000+Tax!$B$10) -> 187248.65 | I13: =IF(OR(Tax!$B$8<=0,Tax!$B$9<=0),Tax!$B$13,(Tax!$B$8+(I8-Tax!$B$8)*Tax!$B$19)*Tax!$B$9/1000+Tax!$B$10) -> 179206.17 | ... T13: =IF(OR(Tax!$B$8<=0,Tax!$B$9<=0),Tax!$B$13,(Tax!$B$8+(T8-Tax!$B$8)*Tax!$B$19)*Tax!$B$9/1000+Tax!$B$10) -> 134972.57
A14: NOI Year 1 (tax-adjusted) | B14: ='Pro Forma'!$D$30+Tax!$B$22-B$13 -> 376910.09 | C14: ='Pro Forma'!$D$30+Tax!$B$22-C$13 -> 406782.13 | D14: ='Pro Forma'!$D$30+Tax!$B$22-D$13 -> 429186.16 | E14: ='Pro Forma'!$D$30+Tax!$B$22-E$13 -> 446611.52 | F14: ='Pro Forma'!$D$30+Tax!$B$22-F$13 -> 460551.8 | G14: ='Pro Forma'!$D$30+Tax!$B$22-G$13 -> 471957.49 | H14: ='Pro Forma'!$D$30+Tax!$B$22-H$13 -> 481462.23 | I14: ='Pro Forma'!$D$30+Tax!$B$22-I$13 -> 489504.7 | ... T14: ='Pro Forma'!$D$30+Tax!$B$22-T$13 -> 533738.31
A15: NOI Year 2 (tax-adjusted) | B15: ='Pro Forma'!$E$30+Tax!$C$22-B$13*(1+Inputs!$B$23)^1 -> 583083.94 | C15: ='Pro Forma'!$E$30+Tax!$C$22-C$13*(1+Inputs!$B$23)^1 -> 613852.14 | D15: ='Pro Forma'!$E$30+Tax!$C$22-D$13*(1+Inputs!$B$23)^1 -> 636928.29 | E15: ='Pro Forma'!$E$30+Tax!$C$22-E$13*(1+Inputs!$B$23)^1 -> 654876.41 | F15: ='Pro Forma'!$E$30+Tax!$C$22-F$13*(1+Inputs!$B$23)^1 -> 669234.91 | G15: ='Pro Forma'!$E$30+Tax!$C$22-G$13*(1+Inputs!$B$23)^1 -> 680982.77 | H15: ='Pro Forma'!$E$30+Tax!$C$22-H$13*(1+Inputs!$B$23)^1 -> 690772.65 | I15: ='Pro Forma'!$E$30+Tax!$C$22-I$13*(1+Inputs!$B$23)^1 -> 699056.4 | ... T15: ='Pro Forma'!$E$30+Tax!$C$22-T$13*(1+Inputs!$B$23)^1 -> 744617
A16: NOI Year 3 (tax-adjusted) | B16: ='Pro Forma'!$F$30+Tax!$D$22-B$13*(1+Inputs!$B$23)^2 -> 612803.34 | C16: ='Pro Forma'!$F$30+Tax!$D$22-C$13*(1+Inputs!$B$23)^2 -> 644494.59 | D16: ='Pro Forma'!$F$30+Tax!$D$22-D$13*(1+Inputs!$B$23)^2 -> 668263.03 | E16: ='Pro Forma'!$F$30+Tax!$D$22-E$13*(1+Inputs!$B$23)^2 -> 686749.59 | F16: ='Pro Forma'!$F$30+Tax!$D$22-F$13*(1+Inputs!$B$23)^2 -> 701538.84 | G16: ='Pro Forma'!$F$30+Tax!$D$22-G$13*(1+Inputs!$B$23)^2 -> 713639.13 | H16: ='Pro Forma'!$F$30+Tax!$D$22-H$13*(1+Inputs!$B$23)^2 -> 723722.71 | I16: ='Pro Forma'!$F$30+Tax!$D$22-I$13*(1+Inputs!$B$23)^2 -> 732254.97 | ... T16: ='Pro Forma'!$F$30+Tax!$D$22-T$13*(1+Inputs!$B$23)^2 -> 779182.4
A17: NOI Year 4 (tax-adjusted) | B17: ='Pro Forma'!$G$30+Tax!$E$22-B$13*(1+Inputs!$B$23)^3 -> 631187.44 | C17: ='Pro Forma'!$G$30+Tax!$E$22-C$13*(1+Inputs!$B$23)^3 -> 663829.42 | D17: ='Pro Forma'!$G$30+Tax!$E$22-D$13*(1+Inputs!$B$23)^3 -> 688310.91 | E17: ='Pro Forma'!$G$30+Tax!$E$22-E$13*(1+Inputs!$B$23)^3 -> 707352.07 | F17: ='Pro Forma'!$G$30+Tax!$E$22-F$13*(1+Inputs!$B$23)^3 -> 722585 | G17: ='Pro Forma'!$G$30+Tax!$E$22-G$13*(1+Inputs!$B$23)^3 -> 735048.3 | H17: ='Pro Forma'!$G$30+Tax!$E$22-H$13*(1+Inputs!$B$23)^3 -> 745434.39 | I17: ='Pro Forma'!$G$30+Tax!$E$22-I$13*(1+Inputs!$B$23)^3 -> 754222.62 | ... T17: ='Pro Forma'!$G$30+Tax!$E$22-T$13*(1+Inputs!$B$23)^3 -> 802557.87
A18: NOI Year 5 (tax-adjusted) | B18: ='Pro Forma'!$H$30+Tax!$F$22-B$13*(1+Inputs!$B$23)^4 -> 650123.06 | C18: ='Pro Forma'!$H$30+Tax!$F$22-C$13*(1+Inputs!$B$23)^4 -> 683744.31 | D18: ='Pro Forma'!$H$30+Tax!$F$22-D$13*(1+Inputs!$B$23)^4 -> 708960.24 | E18: ='Pro Forma'!$H$30+Tax!$F$22-E$13*(1+Inputs!$B$23)^4 -> 728572.63 | F18: ='Pro Forma'!$H$30+Tax!$F$22-F$13*(1+Inputs!$B$23)^4 -> 744262.55 | G18: ='Pro Forma'!$H$30+Tax!$F$22-G$13*(1+Inputs!$B$23)^4 -> 757099.75 | H18: ='Pro Forma'!$H$30+Tax!$F$22-H$13*(1+Inputs!$B$23)^4 -> 767797.42 | I18: ='Pro Forma'!$H$30+Tax!$F$22-I$13*(1+Inputs!$B$23)^4 -> 776849.3 | ... T18: ='Pro Forma'!$H$30+Tax!$F$22-T$13*(1+Inputs!$B$23)^4 -> 826634.6
A19: NOI Year 6 (tax-adjusted) | B19: ='Pro Forma'!$I$30+Tax!$G$22-B$13*(1+Inputs!$B$23)^5 -> 669626.75 | C19: ='Pro Forma'!$I$30+Tax!$G$22-C$13*(1+Inputs!$B$23)^5 -> 704256.63 | D19: ='Pro Forma'!$I$30+Tax!$G$22-D$13*(1+Inputs!$B$23)^5 -> 730229.05 | E19: ='Pro Forma'!$I$30+Tax!$G$22-E$13*(1+Inputs!$B$23)^5 -> 750429.81 | F19: ='Pro Forma'!$I$30+Tax!$G$22-F$13*(1+Inputs!$B$23)^5 -> 766590.42 | G19: ='Pro Forma'!$I$30+Tax!$G$22-G$13*(1+Inputs!$B$23)^5 -> 779812.74 | H19: ='Pro Forma'!$I$30+Tax!$G$22-H$13*(1+Inputs!$B$23)^5 -> 790831.34 | I19: ='Pro Forma'!$I$30+Tax!$G$22-I$13*(1+Inputs!$B$23)^5 -> 800154.77 | ... T19: ='Pro Forma'!$I$30+Tax!$G$22-T$13*(1+Inputs!$B$23)^5 -> 851433.64
A20: NOI Year 7 (tax-adjusted) | B20: ='Pro Forma'!$J$30+Tax!$H$22-B$13*(1+Inputs!$B$23)^6 -> 689715.55 | C20: ='Pro Forma'!$J$30+Tax!$H$22-C$13*(1+Inputs!$B$23)^6 -> 725384.33 | D20: ='Pro Forma'!$J$30+Tax!$H$22-D$13*(1+Inputs!$B$23)^6 -> 752135.92 | E20: ='Pro Forma'!$J$30+Tax!$H$22-E$13*(1+Inputs!$B$23)^6 -> 772942.71 | F20: ='Pro Forma'!$J$30+Tax!$H$22-F$13*(1+Inputs!$B$23)^6 -> 789588.14 | G20: ='Pro Forma'!$J$30+Tax!$H$22-G$13*(1+Inputs!$B$23)^6 -> 803207.13 | H20: ='Pro Forma'!$J$30+Tax!$H$22-H$13*(1+Inputs!$B$23)^6 -> 814556.28 | I20: ='Pro Forma'!$J$30+Tax!$H$22-I$13*(1+Inputs!$B$23)^6 -> 824159.42 | ... T20: ='Pro Forma'!$J$30+Tax!$H$22-T$13*(1+Inputs!$B$23)^6 -> 876976.65
A21: NOI Year 8 (tax-adjusted) | B21: ='Pro Forma'!$K$30+Tax!$I$22-B$13*(1+Inputs!$B$23)^7 -> 710407.02 | C21: ='Pro Forma'!$K$30+Tax!$I$22-C$13*(1+Inputs!$B$23)^7 -> 747145.86 | D21: ='Pro Forma'!$K$30+Tax!$I$22-D$13*(1+Inputs!$B$23)^7 -> 774699.99 | E21: ='Pro Forma'!$K$30+Tax!$I$22-E$13*(1+Inputs!$B$23)^7 -> 796130.99 | F21: ='Pro Forma'!$K$30+Tax!$I$22-F$13*(1+Inputs!$B$23)^7 -> 813275.78 | G21: ='Pro Forma'!$K$30+Tax!$I$22-G$13*(1+Inputs!$B$23)^7 -> 827303.34 | H21: ='Pro Forma'!$K$30+Tax!$I$22-H$13*(1+Inputs!$B$23)^7 -> 838992.97 | I21: ='Pro Forma'!$K$30+Tax!$I$22-I$13*(1+Inputs!$B$23)^7 -> 848884.2 | ... T21: ='Pro Forma'!$K$30+Tax!$I$22-T$13*(1+Inputs!$B$23)^7 -> 903285.95
A22: Gross Exit Value (hold-period NOI / exit cap) | B22: =INDEX(B$14:B$21,Inputs!$B$17)/Inputs!$B$18 -> 10835384 | C22: =INDEX(C$14:C$21,Inputs!$B$17)/Inputs!$B$18 -> 11395738 | D22: =INDEX(D$14:D$21,Inputs!$B$17)/Inputs!$B$18 -> 11816004 | E22: =INDEX(E$14:E$21,Inputs!$B$17)/Inputs!$B$18 -> 12142877 | F22: =INDEX(F$14:F$21,Inputs!$B$17)/Inputs!$B$18 -> 12404376 | G22: =INDEX(G$14:G$21,Inputs!$B$17)/Inputs!$B$18 -> 12618329 | H22: =INDEX(H$14:H$21,Inputs!$B$17)/Inputs!$B$18 -> 12796624 | I22: =INDEX(I$14:I$21,Inputs!$B$17)/Inputs!$B$18 -> 12947488 | ... T22: =INDEX(T$14:T$21,Inputs!$B$17)/Inputs!$B$18 -> 13777243
A23: Loan Payoff at Exit | B23: =IF(Inputs!$B$16=0,B$10-B$12*Inputs!$B$17,B$10*(1+Inputs!$B$16)^Inputs!$B$17-B$12*((1+Inputs!$B$16)^Inputs!$B$17-1)/Inputs!$B$16) -> 12213017 | C23: =IF(Inputs!$B$16=0,C$10-C$12*Inputs!$B$17,C$10*(1+Inputs!$B$16)^Inputs!$B$17-C$12*((1+Inputs!$B$16)^Inputs!$B$17-1)/Inputs!$B$16) -> 10468300 | D23: =IF(Inputs!$B$16=0,D$10-D$12*Inputs!$B$17,D$10*(1+Inputs!$B$16)^Inputs!$B$17-D$12*((1+Inputs!$B$16)^Inputs!$B$17-1)/Inputs!$B$16) -> 9159762.5 | E23: =IF(Inputs!$B$16=0,E$10-E$12*Inputs!$B$17,E$10*(1+Inputs!$B$16)^Inputs!$B$17-E$12*((1+Inputs!$B$16)^Inputs!$B$17-1)/Inputs!$B$16) -> 8142011.1 | F23: =IF(Inputs!$B$16=0,F$10-F$12*Inputs!$B$17,F$10*(1+Inputs!$B$16)^Inputs!$B$17-F$12*((1+Inputs!$B$16)^Inputs!$B$17-1)/Inputs!$B$16) -> 7327810 | G23: =IF(Inputs!$B$16=0,G$10-G$12*Inputs!$B$17,G$10*(1+Inputs!$B$16)^Inputs!$B$17-G$12*((1+Inputs!$B$16)^Inputs!$B$17-1)/Inputs!$B$16) -> 6661645.5 | H23: =IF(Inputs!$B$16=0,H$10-H$12*Inputs!$B$17,H$10*(1+Inputs!$B$16)^Inputs!$B$17-H$12*((1+Inputs!$B$16)^Inputs!$B$17-1)/Inputs!$B$16) -> 6106508.3 | I23: =IF(Inputs!$B$16=0,I$10-I$12*Inputs!$B$17,I$10*(1+Inputs!$B$16)^Inputs!$B$17-I$12*((1+Inputs!$B$16)^Inputs!$B$17-1)/Inputs!$B$16) -> 5636776.9 | ... T23: =IF(Inputs!$B$16=0,T$10-T$12*Inputs!$B$17,T$10*(1+Inputs!$B$16)^Inputs!$B$17-T$12*((1+Inputs!$B$16)^Inputs!$B$17-1)/Inputs!$B$16) -> 3053254.2
A24: Net Sale Proceeds (less disposition cost) | B24: =B22*(1-Inputs!$B$19)-B23 -> -1919401.5 | C24: =C22*(1-Inputs!$B$19)-C23 -> 357651.52 | D24: =D22*(1-Inputs!$B$19)-D23 -> 2065441.3 | E24: =E22*(1-Inputs!$B$19)-E23 -> 3393722.3 | F24: =F22*(1-Inputs!$B$19)-F23 -> 4456347 | G24: =G22*(1-Inputs!$B$19)-G23 -> 5325767.3 | H24: =H22*(1-Inputs!$B$19)-H23 -> 6050284.2 | I24: =I22*(1-Inputs!$B$19)-I23 -> 6663336.9 | ... T24: =T22*(1-Inputs!$B$19)-T23 -> 10035127
A25: Equity Cash Flow - Year 0 | B25: =-B11 -> -6641165 | C25: =-C11 -> -5818655.7 | D25: =-D11 -> -5201773.8 | E25: =-E11 -> -4721976.7 | F25: =-F11 -> -4338139 | G25: =-G11 -> -4024090 | H25: =-H11 -> -3762382.5 | I25: =-I11 -> -3540937.7 | ... T25: =-T11 -> -2322991.3
A26: Equity Cash Flow - Year 1 | B26: =IF(Inputs!$B$17<1,0,B14-B$12+IF(Inputs!$B$17=1,B$24,0)) -> -294805.83 | C26: =IF(Inputs!$B$17<1,0,C14-C$12+IF(Inputs!$B$17=1,C$24,0)) -> -168974.37 | D26: =IF(Inputs!$B$17<1,0,D14-D$12+IF(Inputs!$B$17=1,D$24,0)) -> -74600.779 | E26: =IF(Inputs!$B$17<1,0,E14-E$12+IF(Inputs!$B$17=1,E$24,0)) -> -1199.0946 | F26: =IF(Inputs!$B$17<1,0,F14-F$12+IF(Inputs!$B$17=1,F$24,0)) -> 57522.253 | G26: =IF(Inputs!$B$17<1,0,G14-G$12+IF(Inputs!$B$17=1,G$24,0)) -> 105566.99 | H26: =IF(Inputs!$B$17<1,0,H14-H$12+IF(Inputs!$B$17=1,H$24,0)) -> 145604.27 | I26: =IF(Inputs!$B$17<1,0,I14-I$12+IF(Inputs!$B$17=1,I$24,0)) -> 179481.97 | ... T26: =IF(Inputs!$B$17<1,0,T14-T$12+IF(Inputs!$B$17=1,T$24,0)) -> 365809.33
A27: Equity Cash Flow - Year 2 | B27: =IF(Inputs!$B$17<2,0,B15-B$12+IF(Inputs!$B$17=2,B$24,0)) -> -88631.978 | C27: =IF(Inputs!$B$17<2,0,C15-C$12+IF(Inputs!$B$17=2,C$24,0)) -> 38095.642 | D27: =IF(Inputs!$B$17<2,0,D15-D$12+IF(Inputs!$B$17=2,D$24,0)) -> 133141.36 | E27: =IF(Inputs!$B$17<2,0,E15-E$12+IF(Inputs!$B$17=2,E$24,0)) -> 207065.8 | F27: =IF(Inputs!$B$17<2,0,F15-F$12+IF(Inputs!$B$17=2,F$24,0)) -> 266205.36 | G27: =IF(Inputs!$B$17<2,0,G15-G$12+IF(Inputs!$B$17=2,G$24,0)) -> 314592.27 | H27: =IF(Inputs!$B$17<2,0,H15-H$12+IF(Inputs!$B$17=2,H$24,0)) -> 354914.69 | I27: =IF(Inputs!$B$17<2,0,I15-I$12+IF(Inputs!$B$17=2,I$24,0)) -> 389033.67 | ... T27: =IF(Inputs!$B$17<2,0,T15-T$12+IF(Inputs!$B$17=2,T$24,0)) -> 576688.03
A28: Equity Cash Flow - Year 3 | B28: =IF(Inputs!$B$17<3,0,B16-B$12+IF(Inputs!$B$17=3,B$24,0)) -> -58912.577 | C28: =IF(Inputs!$B$17<3,0,C16-C$12+IF(Inputs!$B$17=3,C$24,0)) -> 68738.088 | D28: =IF(Inputs!$B$17<3,0,D16-D$12+IF(Inputs!$B$17=3,D$24,0)) -> 164476.09 | E28: =IF(Inputs!$B$17<3,0,E16-E$12+IF(Inputs!$B$17=3,E$24,0)) -> 238938.98 | F28: =IF(Inputs!$B$17<3,0,F16-F$12+IF(Inputs!$B$17=3,F$24,0)) -> 298509.29 | G28: =IF(Inputs!$B$17<3,0,G16-G$12+IF(Inputs!$B$17=3,G$24,0)) -> 347248.63 | H28: =IF(Inputs!$B$17<3,0,H16-H$12+IF(Inputs!$B$17=3,H$24,0)) -> 387864.75 | I28: =IF(Inputs!$B$17<3,0,I16-I$12+IF(Inputs!$B$17=3,I$24,0)) -> 422232.24 | ... T28: =IF(Inputs!$B$17<3,0,T16-T$12+IF(Inputs!$B$17=3,T$24,0)) -> 611253.42
A29: Equity Cash Flow - Year 4 | B29: =IF(Inputs!$B$17<4,0,B17-B$12+IF(Inputs!$B$17=4,B$24,0)) -> -40528.478 | C29: =IF(Inputs!$B$17<4,0,C17-C$12+IF(Inputs!$B$17=4,C$24,0)) -> 88072.925 | D29: =IF(Inputs!$B$17<4,0,D17-D$12+IF(Inputs!$B$17=4,D$24,0)) -> 184523.98 | E29: =IF(Inputs!$B$17<4,0,E17-E$12+IF(Inputs!$B$17=4,E$24,0)) -> 259541.46 | F29: =IF(Inputs!$B$17<4,0,F17-F$12+IF(Inputs!$B$17=4,F$24,0)) -> 319555.45 | G29: =IF(Inputs!$B$17<4,0,G17-G$12+IF(Inputs!$B$17=4,G$24,0)) -> 368657.8 | H29: =IF(Inputs!$B$17<4,0,H17-H$12+IF(Inputs!$B$17=4,H$24,0)) -> 409576.43 | I29: =IF(Inputs!$B$17<4,0,I17-I$12+IF(Inputs!$B$17=4,I$24,0)) -> 444199.89 | ... T29: =IF(Inputs!$B$17<4,0,T17-T$12+IF(Inputs!$B$17=4,T$24,0)) -> 634628.89
A30: Equity Cash Flow - Year 5 | B30: =IF(Inputs!$B$17<5,0,B18-B$12+IF(Inputs!$B$17=5,B$24,0)) -> -1940994.4 | C30: =IF(Inputs!$B$17<5,0,C18-C$12+IF(Inputs!$B$17=5,C$24,0)) -> 465639.33 | D30: =IF(Inputs!$B$17<5,0,D18-D$12+IF(Inputs!$B$17=5,D$24,0)) -> 2270614.6 | E30: =IF(Inputs!$B$17<5,0,E18-E$12+IF(Inputs!$B$17=5,E$24,0)) -> 3674484.3 | F30: =IF(Inputs!$B$17<5,0,F18-F$12+IF(Inputs!$B$17=5,F$24,0)) -> 4797580 | G30: =IF(Inputs!$B$17<5,0,G18-G$12+IF(Inputs!$B$17=5,G$24,0)) -> 5716476.5 | H30: =IF(Inputs!$B$17<5,0,H18-H$12+IF(Inputs!$B$17=5,H$24,0)) -> 6482223.6 | I30: =IF(Inputs!$B$17<5,0,I18-I$12+IF(Inputs!$B$17=5,I$24,0)) -> 7130163.5 | ... T30: =IF(Inputs!$B$17<5,0,T18-T$12+IF(Inputs!$B$17=5,T$24,0)) -> 10693833
A31: Equity Cash Flow - Year 6 | B31: =IF(Inputs!$B$17<6,0,B19-B$12+IF(Inputs!$B$17=6,B$24,0)) -> 0 | C31: =IF(Inputs!$B$17<6,0,C19-C$12+IF(Inputs!$B$17=6,C$24,0)) -> 0 | D31: =IF(Inputs!$B$17<6,0,D19-D$12+IF(Inputs!$B$17=6,D$24,0)) -> 0 | E31: =IF(Inputs!$B$17<6,0,E19-E$12+IF(Inputs!$B$17=6,E$24,0)) -> 0 | F31: =IF(Inputs!$B$17<6,0,F19-F$12+IF(Inputs!$B$17=6,F$24,0)) -> 0 | G31: =IF(Inputs!$B$17<6,0,G19-G$12+IF(Inputs!$B$17=6,G$24,0)) -> 0 | H31: =IF(Inputs!$B$17<6,0,H19-H$12+IF(Inputs!$B$17=6,H$24,0)) -> 0 | I31: =IF(Inputs!$B$17<6,0,I19-I$12+IF(Inputs!$B$17=6,I$24,0)) -> 0 | ... T31: =IF(Inputs!$B$17<6,0,T19-T$12+IF(Inputs!$B$17=6,T$24,0)) -> 0
A32: Equity Cash Flow - Year 7 | B32: =IF(Inputs!$B$17<7,0,B20-B$12+IF(Inputs!$B$17=7,B$24,0)) -> 0 | C32: =IF(Inputs!$B$17<7,0,C20-C$12+IF(Inputs!$B$17=7,C$24,0)) -> 0 | D32: =IF(Inputs!$B$17<7,0,D20-D$12+IF(Inputs!$B$17=7,D$24,0)) -> 0 | E32: =IF(Inputs!$B$17<7,0,E20-E$12+IF(Inputs!$B$17=7,E$24,0)) -> 0 | F32: =IF(Inputs!$B$17<7,0,F20-F$12+IF(Inputs!$B$17=7,F$24,0)) -> 0 | G32: =IF(Inputs!$B$17<7,0,G20-G$12+IF(Inputs!$B$17=7,G$24,0)) -> 0 | H32: =IF(Inputs!$B$17<7,0,H20-H$12+IF(Inputs!$B$17=7,H$24,0)) -> 0 | I32: =IF(Inputs!$B$17<7,0,I20-I$12+IF(Inputs!$B$17=7,I$24,0)) -> 0 | ... T32: =IF(Inputs!$B$17<7,0,T20-T$12+IF(Inputs!$B$17=7,T$24,0)) -> 0
A33: Equity Cash Flow - Year 8 | B33: =IF(Inputs!$B$17<8,0,B21-B$12+IF(Inputs!$B$17=8,B$24,0)) -> 0 | C33: =IF(Inputs!$B$17<8,0,C21-C$12+IF(Inputs!$B$17=8,C$24,0)) -> 0 | D33: =IF(Inputs!$B$17<8,0,D21-D$12+IF(Inputs!$B$17=8,D$24,0)) -> 0 | E33: =IF(Inputs!$B$17<8,0,E21-E$12+IF(Inputs!$B$17=8,E$24,0)) -> 0 | F33: =IF(Inputs!$B$17<8,0,F21-F$12+IF(Inputs!$B$17=8,F$24,0)) -> 0 | G33: =IF(Inputs!$B$17<8,0,G21-G$12+IF(Inputs!$B$17=8,G$24,0)) -> 0 | H33: =IF(Inputs!$B$17<8,0,H21-H$12+IF(Inputs!$B$17=8,H$24,0)) -> 0 | I33: =IF(Inputs!$B$17<8,0,I21-I$12+IF(Inputs!$B$17=8,I$24,0)) -> 0 | ... T33: =IF(Inputs!$B$17<8,0,T21-T$12+IF(Inputs!$B$17=8,T$24,0)) -> 0
A34: Levered IRR | B34: =IFERROR(IRR(B25:B33),0) -> -1 | C34: =IFERROR(IRR(C25:C33),0) -> -0.38054016 | D34: =IFERROR(IRR(D25:D33),0) -> -0.12944885 | E34: =IFERROR(IRR(E25:E33),0) -> -0.015938834 | F34: =IFERROR(IRR(F25:F33),0) -> 0.062206473 | G34: =IFERROR(IRR(G25:G33),0) -> 0.12281181 | H34: =IFERROR(IRR(H25:H33),0) -> 0.1726762 | I34: =IFERROR(IRR(I25:I33),0) -> 0.21518976 | ... T34: =IFERROR(IRR(T25:T33),0) -> 0.48225889
A35: Year 2 Cash-on-Cash | B35: =B27/B11 -> -0.013345848 | C35: =C27/C11 -> 0.0065471552 | D35: =D27/D11 -> 0.025595376 | E35: =E27/E11 -> 0.043851509 | F35: =F27/F11 -> 0.061363953 | G35: =G27/G11 -> 0.078177244 | H35: =H27/H11 -> 0.094332432 | I35: =I27/I11 -> 0.10986741 | ... T35: =T27/T11 -> 0.24825235
A36: IRR vs Target | B36: =IF(B34>=Inputs!$B$47,"PASS","FLAG") -> FLAG | C36: =IF(C34>=Inputs!$B$47,"PASS","FLAG") -> FLAG | D36: =IF(D34>=Inputs!$B$47,"PASS","FLAG") -> FLAG | E36: =IF(E34>=Inputs!$B$47,"PASS","FLAG") -> FLAG | F36: =IF(F34>=Inputs!$B$47,"PASS","FLAG") -> FLAG | G36: =IF(G34>=Inputs!$B$47,"PASS","FLAG") -> FLAG | H36: =IF(H34>=Inputs!$B$47,"PASS","FLAG") -> PASS | I36: =IF(I34>=Inputs!$B$47,"PASS","FLAG") -> PASS | ... T36: =IF(T34>=Inputs!$B$47,"PASS","FLAG") -> PASS
A37: Yr2 CoC vs Target | B37: =IF(B35>=Inputs!$B$48,"PASS","FLAG") -> FLAG | C37: =IF(C35>=Inputs!$B$48,"PASS","FLAG") -> FLAG | D37: =IF(D35>=Inputs!$B$48,"PASS","FLAG") -> FLAG | E37: =IF(E35>=Inputs!$B$48,"PASS","FLAG") -> PASS | F37: =IF(F35>=Inputs!$B$48,"PASS","FLAG") -> PASS | G37: =IF(G35>=Inputs!$B$48,"PASS","FLAG") -> PASS | H37: =IF(H35>=Inputs!$B$48,"PASS","FLAG") -> PASS | I37: =IF(I35>=Inputs!$B$48,"PASS","FLAG") -> PASS | ... T37: =IF(T35>=Inputs!$B$48,"PASS","FLAG") -> PASS
A39: SOLVED: MAXIMUM PRICE TO HIT THE IRR TARGET
A40: Columns failing the target (helper) | B40: =COUNTIF(B34:T34,"<"&Inputs!$B$47) -> 6 | D40: Counts candidate caps whose IRR is below target; used to bracket the solve.
A41: Solved Purchase Cap Rate @ IRR Target | B41: =IF(B40=0,"Below 3.00% - not achievable in range",IF(B40>=19,"Above 12.00% - not achievable in range",INDEX(B7:T7,B40)+(INDEX(B7:T7,B40+1)-INDEX(B7:T7,B40))*(Inputs!$B$47-INDEX(B34:T34,B40))/(INDEX(B34:T34,B40+1)-INDEX(B34:T34,B40)))) -> 0.058728933 | D41: Linear interpolation between the two caps bracketing the IRR target; if every column passes, expand the range to lower cap rates.
A42: Max Purchase Price @ IRR Target | B42: =IF(ISNUMBER(B41),'T12 Actuals'!$B$23/B41,"-") -> 8912387.4
A43: Max Price Per Unit | B43: =IF(ISNUMBER(B42),B42/Inputs!$B$13,"-") -> 92837.369 | D43: Solved price / total units.
A44: Discount vs Current Cap-Rate Basis | B44: =IF(ISNUMBER(B42),1-B42/'Debt & Exit'!$B$6,"-") -> -0.055697712 | D44: How far below the current cap-rate-derived basis the offer must be to clear the IRR target.
A45: Year 2 Cash-on-Cash at Solved Price | B45: =IF(ISNUMBER(B41),IF(B40=0,INDEX(B35:T35,1),INDEX(B35:T35,B40)+(INDEX(B35:T35,B40+1)-INDEX(B35:T35,B40))*(Inputs!$B$47-INDEX(B34:T34,B40))/(INDEX(B34:T34,B40+1)-INDEX(B34:T34,B40))),"-") -> 0.090225566
A47: Note: the solver sells in the Inputs hold-period year (Years 1-8 are all modeled). Changing any Inputs assumption re-solves automatically.

Sheet Price Tool
A1: Price Tool - pick a purchase cap rate, read the price and the returns
A3: Purchase cap rate (pick one) | B3: 0.06 | C3: Click the box and choose from the list. The price is the T12 NOI divided by this cap rate; everything below reprices at it. | D3: =MATCH(ROUND($B$3,4),'Max Price Solver'!$B$7:$T$7,0) -> 7
A5: Purchase price | B5: =IFERROR(INDEX('Max Price Solver'!$B$8:$T$8,$D$3),"n/a") -> 8723583.3
A6: Price per unit | B6: =IFERROR(INDEX('Max Price Solver'!$B$9:$T$9,$D$3),"n/a") -> 90870.66
A7: Loan amount | B7: =IFERROR(INDEX('Max Price Solver'!$B$10:$T$10,$D$3),"n/a") -> 6106508.3 | C7: at the Inputs tab's loan-to-value
A8: Initial equity required | B8: =IFERROR(INDEX('Max Price Solver'!$B$11:$T$11,$D$3),"n/a") -> 3762382.5 | C8: price + capex + closing costs, less the loan
A9: Annual debt service | B9: =IFERROR(INDEX('Max Price Solver'!$B$12:$T$12,$D$3),"n/a") -> 335857.96
A10: Year-1 NOI (tax-adjusted) | B10: =IFERROR(INDEX('Max Price Solver'!$B$14:$T$14,$D$3),"n/a") -> 481462.23 | C10: Pro Forma NOI with property tax repriced at this price
A11: Year-2 NOI (tax-adjusted) | B11: =IFERROR(INDEX('Max Price Solver'!$B$15:$T$15,$D$3),"n/a") -> 690772.65
A12: Gross exit value | B12: =IFERROR(INDEX('Max Price Solver'!$B$22:$T$22,$D$3),"n/a") -> 12796624 | C12: at the hold-period year
A13: Net sale proceeds | B13: =IFERROR(INDEX('Max Price Solver'!$B$24:$T$24,$D$3),"n/a") -> 6050284.2 | C13: after disposition cost and loan payoff
A14: Levered IRR | B14: =IFERROR(INDEX('Max Price Solver'!$B$34:$T$34,$D$3),"n/a") -> 0.1726762
A15: Year-2 cash-on-cash | B15: =IFERROR(INDEX('Max Price Solver'!$B$35:$T$35,$D$3),"n/a") -> 0.094332432
A16: Levered IRR vs target | B16: =IFERROR(INDEX('Max Price Solver'!$B$36:$T$36,$D$3),"n/a") -> PASS
A17: Year-2 cash-on-cash vs target | B17: =IFERROR(INDEX('Max Price Solver'!$B$37:$T$37,$D$3),"n/a") -> PASS
A19: The price that just hits your IRR target
A20: Max purchase price at the IRR target | B20: ='Max Price Solver'!$B$42 -> 8912387.4
A21: Max price per unit | B21: ='Max Price Solver'!$B$43 -> 92837.369
A22: Purchase cap rate that gives it | B22: ='Max Price Solver'!$B$41 -> 0.058728933
A23: Year-2 cash-on-cash at that price | B23: ='Max Price Solver'!$B$45 -> 0.090225566
A25: The full grid of 19 cap rates is on the Max Price Solver tab; this tab only reads from it.

Sheet Checks
A1: Model Checks and Decision Readiness
A2: =COUNTIF(B6:B20,"OK") -> 12 | B2: =COUNTIF(B6:B20,"NEEDS INPUT") -> 2 | C2: =COUNTIF(B6:B20,"WARN") -> 1 | D2: =COUNTIF(B6:B20,"PARTIAL")+COUNTIF(B6:B20,"REVIEW") -> 0
A3: OK | B3: NEEDS INPUT | C3: WARN | D3: PARTIAL/REVIEW
A5: Check | B5: Result | C5: Severity | D5: Notes
A6: Purchase price formula | B6: =IF(Inputs!$B$6>0,"OK (override)",IF(ABS('Debt & Exit'!$B$6-'T12 Actuals'!$B$23/Inputs!$B$14)<1,"OK","WARN")) -> OK | C6: High | D6: Purchase price = T12 NOI / cap, or the manual override on Inputs. OK if formula returns OK.
A7: LTV set to 70% | B7: =IF(Inputs!$B$15=70%,"OK","WARN") -> OK | C7: High | D7: Checks Inputs LTV = 70%. OK if formula returns OK.
A8: Bad debt set to 2% | B8: =IF(Inputs!$B$24=2%,"OK","WARN") -> OK | C8: High | D8: Checks Inputs bad debt = 2%. OK if formula returns OK.
A9: Upfront and exit costs | B9: =IF(AND(Inputs!$B$20=3%,Inputs!$B$19=5%),"OK","WARN") -> OK | C9: High | D9: Checks upfront closing cost is 3% and exit cost is 5%. OK if formula returns OK.
A10: Rent roll unit count tie | B10: =IF('Rent Roll'!$B$11='Rent Roll'!$B$7,"OK","WARN") -> OK | C10: Medium | D10: Checks parsed unit count ties to the official rent roll unit count. If WARN, review rent roll parsing.
A11: Official vs parsed occupied units | B11: =IF('Rent Roll'!$B$12='Rent Roll'!$B$8,"OK","WARN") -> OK | C11: Medium | D11: Compares official occupied count to parsed rent-charge occupied count. Review discrepancy before final.
A12: Property tax modeled | B12: =IF(Tax!$B$22>0,"OK","WARN") -> OK | C12: High | D12: Checks projected Year 1 property tax is nonzero. If only T12 tax is available, replace with county-specific estimate when diligence supports it.
A13: Apartments.com/Zillow rent comps | B13: =IF(COUNTIF('Rent Comps'!$A$7:$A$11,"[Comp*")=5,"NEEDS INPUT",IF(COUNTIF('Rent Comps'!$A$7:$A$11,"[Comp*")>0,"PARTIAL","OK")) -> OK | C13: High | D13: Add OM comp set + online verification on Rent Comps tab. Paste verified comps or support from browser/CoStar.
A14: Sale comps | B14: =IF(COUNTIF('Sale Comps'!$A$6:$A$7,"[Sale comp*")=2,"NEEDS INPUT",IF(COUNTIF('Sale Comps'!$A$6:$A$7,"[Sale comp*")>0,"PARTIAL","OK")) -> OK | C14: High | D14: Add recent comparable sales on Sale Comps tab (CoStar/Crexi/county records). Need 3-5 recent comparable sales.
A15: Debt quote | B15: NEEDS INPUT | C15: High | D15: Interest rate is placeholder until lender quote. Get rate, amortization, IO period, fees, reserves.
A16: Capex scope | B16: NEEDS INPUT | C16: High | D16: Capex budget carried from prior model and needs confirmation. Confirm bids/scope/contingency/timing.
A17: Renovation rent downtime included | B17: =IF('Reno Pace'!$B$115>0,"OK","WARN") -> OK | C17: High | D17: Checks Reno Pace has rent downtime from current average rent and units offline. OK if downtime is greater than zero.
A18: IRR includes sale proceeds | B18: =IF(INDEX('Debt & Exit'!$C$24:$J$24,Inputs!$B$17)>INDEX('Debt & Exit'!$C$22:$J$22,Inputs!$B$17),"OK","WARN") -> OK | C18: High | D18: Checks the exit-year cash flow includes net sale proceeds. OK if sale proceeds land in the Inputs hold-period year.
A19: Hold period inside the modeled range | B19: =IF(AND(Inputs!$B$17>=1,Inputs!$B$17<=8),"OK","WARN") -> OK | C19: High | D19: The pro forma runs Years 1-8. A hold period outside that range leaves the sale unmodeled.
A20: Year 1 total opex within house cap | B20: =IF(Inputs!$B$55<=0,"NEEDS INPUT",IF('Pro Forma'!$D$29<='Pro Forma'!$D$15*Inputs!$B$55,"OK","WARN")) -> WARN | C20: High | D20: House ceiling from the 2026-08-10 benchmarks: total operating expenses no more than 50% of effective gross income in Year 1. WARN means the deal is underwritten above the house cap.

Sheet Rent Comps
A1: Rent Comps - OM Comp Set + Online Verification, Fairness-Checked (5 total)
A2: =IF(IFERROR(G6,0)=0,"n/a",G6) -> 1086.2173 | B2: =IF(IFERROR(G12,0)=0,"n/a",G12) -> 1150 | C2: =IF(IFERROR(L6,0)=0,"n/a",L6) -> 0.9375 | D2: =IF(IFERROR(L12,0)=0,"n/a",L12) -> 0.938
A3: SUBJECT ACHIEVED RENT | B3: COMP SET AVG RENT | C3: SUBJECT OCCUPANCY | D3: COMP SET AVG OCCUPANCY
A5: Property | B5: Address / Market | C5: Units | D5: Year Built / Renovated | E5: Avg Unit Size SF | F5: OM Market Rent | G5: OM Achieved Rent | H5: OM Rent PSF | I5: Apartments.com / Zillow Rent | J5: Source Status | K5: Notes | L5: Occupancy | M5: Fair Comp?
A6: =Inputs!$B$9&" (subject)" -> Riverbend Apartments (subject) | B6: =Inputs!$B$10 -> 4100 Millrace Pointe Drive, Dayton, OH 45415 | C6: =Inputs!$B$13 -> 96 | D6: =Inputs!$B$11 -> 1987 | E6: ='Unit Mix'!$B$2 -> 898.44583 | F6: ='Unit Mix'!$C$2 -> 1136.8231 | G6: ='Unit Mix'!$D$2 -> 1086.2173 | H6: =IFERROR('Unit Mix'!$D$2/'Unit Mix'!$B$2,0) -> 1.2089959 | I6: n/a (subject) | J6: OM p.13/p.68 | K6: Auto-filled from Inputs / Unit Mix. | L6: ='Rent Roll'!$B$10 -> 0.9375 | M6: -
A7: Stillwater Crossing | B7: Dayton, OH - Northridge | C7: 112 | D7: 1989 | E7: 930 | F7: 1165 | G7: 1130 | H7: 1.22 | J7: OM p.9 | K7: Renovated interiors, similar finishes | L7: 0.94
A8: The Oaks at Miamisburg Pike | B8: Miamisburg, OH | C8: 88 | D8: 1985 | E8: 905 | F8: 1140 | G8: 1105 | H8: 1.22 | J8: OM p.9 | K8: Partial interior upgrades | L8: 0.95
A9: Kettering Green | B9: Kettering, OH | C9: 120 | D9: 1991 | E9: 960 | F9: 1235 | G9: 1200 | H9: 1.25 | J9: OM p.9 | K9: Fully renovated, pool and fitness | L9: 0.93
A10: Brookhaven Terrace | B10: Huber Heights, OH | C10: 104 | D10: 1988 | E10: 915 | F10: 1090 | G10: 1060 | H10: 1.19 | J10: OM p.9 | K10: Classic finishes, no renovation | L10: 0.92
A11: Westbrook Landing | B11: Centerville, OH | C11: 96 | D11: 1993 | E11: 985 | F11: 1295 | G11: 1255 | H11: 1.28 | J11: OM p.9 | K11: Newer vintage, attached garages | L11: 0.95
A12: COMP SET AVERAGE | B12: - | C12: =IFERROR(AVERAGE(C7:C11),0) -> 104 | D12: - | E12: =IFERROR(AVERAGE(E7:E11),0) -> 939 | F12: =IFERROR(AVERAGE(F7:F11),0) -> 1185 | G12: =IFERROR(AVERAGE(G7:G11),0) -> 1150 | H12: =IFERROR(AVERAGE(H7:H11),0) -> 1.232 | I12: - | J12: Calculated | K12: Average of comps with published figures. Note which comps are OM-sourced vs online-verified, and check year built / unit size / unit count so comparisons are ACTUALLY fair. | L12: =IFERROR(AVERAGE(L7:L11),0) -> 0.938 | M12: -

Sheet Sale Comps
A1: Sale Comps - recent market transactions (auto-searched online + OM when available; verify before relying on them)
A2: =IF(IFERROR(G12,0)=0,"n/a",G12) -> 87939.348 | B2: =IF(IFERROR(IFERROR(AVERAGE(G6:G11),0),0)=0,"n/a",IFERROR(AVERAGE(G6:G11),0)) -> 88504 | C2: =IF(IFERROR(G6,0)=0,"n/a",G6) -> 85000 | D2: =IF(IFERROR(IFERROR(A2/B2-1,0),0)=0,"n/a",IFERROR(A2/B2-1,0)) -> -0.0063799589
A3: SUBJECT PRICE/DOOR (ASK) | B3: MARKET MEDIAN/DOOR | C3: BEST COMP $/DOOR | D3: SUBJECT vs COMP AVG
A5: Property | B5: Location | C5: Units | D5: Year Built | E5: Sale Date | F5: Sale Price | G5: Price/Unit | H5: Buyer/Seller | I5: Source | J5: Fair Comp? | K5: Notes
A6: Stillwater Crossing | B6: Dayton, OH | C6: 112 | D6: 1989 | E6: 2026-03 | F6: 9520000 | G6: 85000 | I6: OM p.10 | K6: 6.4% cap, value-add
A7: Pine Hollow Apartments | B7: Springboro, OH | C7: 80 | D7: 1990 | E7: 2025-11 | F7: 7440000 | G7: 93000 | I7: OM p.10 | K7: 6.1% cap
A8: Courtyard at Wolf Creek | B8: Trotwood, OH | C8: 128 | D8: 1984 | E8: 2025-09 | F8: 9730000 | G8: 76016 | I8: OM p.10 | K8: 6.8% cap, light value-add
A9: Kettering Green | B9: Kettering, OH | C9: 120 | D9: 1991 | E9: 2026-06 | F9: 12000000 | G9: 100000 | I9: OM p.10 | K9: 5.9% cap, renovated
A12: Subject (for reference) | B12: =Inputs!$B$10 -> 4100 Millrace Pointe Drive, Dayton, OH 45415 | C12: =Inputs!$B$13 -> 96 | D12: =Inputs!$B$11 -> 1987 | E12: Proposed | F12: ='Debt & Exit'!$B$6 -> 8442177.4 | G12: ='Debt & Exit'!$B$7 -> 87939.348
A13: 2. Free supplemental source: county property records or recorder data can verify a known comp property's recorded sale price/date where available.
A14: 3. Broker relationships: ask active multifamily brokers and lenders for recent transaction comps in the subject submarket.
A15: 4. Public search is a supplement only; full closed-comp pricing, cap rates, buyer/seller, and financing usually require CoStar, Yardi Matrix, Crexi, broker packages, or county records.
A16: 2. Free check: the county assessor / recorder shows the actual recorded sale price and date for any specific comp property once you know the parcel.
A17: 3. Broker reports: JLL, Cushman & Wakefield, Northmarq, and Berkadia publish periodic metro multifamily transaction reports (some free) with named recent deals - worth requesting directly.
A18: 4. Comp rows with a source URL were found by automated public web search - verify each before relying on it; public search cannot reliably surface every recent closed deal.
